[{"operadora": "Vivo", "tecnologia": "3G", "municipio": "Belém", "lat": -1.33833, "lon": -48.45778, "data": "26/08/2014", "nova": false}, {"operadora": "Vivo", "tecnologia": "4G", "municipio": "Belém", "lat": -1.33833, "lon": -48.45778, "data": "26/08/2014", "nova": false}, {"operadora": "Vivo", "tecnologia": "5G", "municipio": "Belém", "lat": -1.33833, "lon": -48.45778, "data": "26/08/2014", "nova": false}, {"operadora": "TIM", "tecnologia": "4G", "municipio": "Ananindeua", "lat": -1.33833, "lon": -48.375, "data": "06/08/2019", "nova": false}, {"operadora": "TIM", "tecnologia": "5G", "municipio": "Ananindeua", "lat": -1.33833, "lon": -48.375, "data": "06/08/2019", "nova": false}, {"operadora": "TIM", "tecnologia": "4G", "municipio": "Ananindeua", "lat": -1.33825, "lon": -48.392444, "data": "27/05/2004", "nova": false}, {"operadora": "TIM", "tecnologia": "2G", "municipio": "Ananindeua", "lat": -1.33825, "lon": -48.392444, "data": "27/05/2004", "nova": false}, {"operadora": "TIM", "tecnologia": "3G", "municipio": "Ananindeua", "lat": -1.33825, "lon": -48.392444, "data": "27/05/2004", "nova": false}, {"operadora": "TIM", "tecnologia": "5G", "municipio": "Ananindeua", "lat": -1.33825, "lon": -48.392444, "data": "27/05/2004", "nova": false}, {"operadora": "Claro", "tecnologia": "3G", "municipio": "Belém", "lat": -1.33806, "lon": -48.47919, "data": "23/03/2018", "nova": false}, {"operadora": "Claro", "tecnologia": "4G", "municipio": "Belém", "lat": -1.33806, "lon": -48.47919, "data": "23/03/2018", "nova": false}, {"operadora": "Claro", "tecnologia": "5G", "municipio": "Belém", "lat": -1.33806, "lon": -48.47919, "data": "23/03/2018", "nova": false}, {"operadora": "TIM", "tecnologia": "4G", "municipio": "Ananindeua", "lat": -1.33806, "lon": -48.40694, "data": "30/04/2020", "nova": false}, {"operadora": "Claro", "tecnologia": "4G", "municipio": "Ananindeua", "lat": -1.33747, "lon": -48.38472, "data": "08/07/2008", "nova": false}, {"operadora": "Claro", "tecnologia": "3G", "municipio": "Ananindeua", "lat": -1.33747, "lon": -48.38472, "data": "08/07/2008", "nova": false}, {"operadora": "Claro", "tecnologia": "2G", "municipio": "Ananindeua", "lat": -1.33747, "lon": -48.38472, "data": "08/07/2008", "nova": false}, {"operadora": "Claro", "tecnologia": "5G", "municipio": "Ananindeua", "lat": -1.33747, "lon": -48.38472, "data": "08/07/2008", "nova": false}, {"operadora": "Claro", "tecnologia": "2G", "municipio": "Ananindeua", "lat": -1.337222, "lon": -48.384722, "data": "24/10/2022", "nova": false}, {"operadora": "Vivo", "tecnologia": "3G", "municipio": "Ananindeua", "lat": -1.33694, "lon": -48.38472, "data": "11/08/2021", "nova": false}, {"operadora": "Vivo", "tecnologia": "2G", "municipio": "Ananindeua", "lat": -1.33694, "lon": -48.38472, "data": "11/08/2021", "nova": false}, {"operadora": "Vivo", "tecnologia": "4G", "municipio": "Ananindeua", "lat": -1.33694, "lon": -48.38472, "data": "11/08/2021", "nova": false}, {"operadora": "Vivo", "tecnologia": "5G", "municipio": "Ananindeua", "lat": -1.33694, "lon": -48.38472, "data": "11/08/2021", "nova": false}, {"operadora": "TIM", "tecnologia": "4G", "municipio": "Ananindeua", "lat": -1.336639, "lon": -48.361556, "data": "17/01/2020", "nova": false}, {"operadora": "TIM", "tecnologia": "2G", "municipio": "Ananindeua", "lat": -1.336583, "lon": -48.384603, "data": "27/09/2005", "nova": false}, {"operadora": "TIM", "tecnologia": "4G", "municipio": "Ananindeua", "lat": -1.336583, "lon": -48.384603, "data": "27/09/2005", "nova": false}, {"operadora": "TIM", "tecnologia": "3G", "municipio": "Ananindeua", "lat": -1.336583, "lon": -48.384603, "data": "27/09/2005", "nova": false}, {"operadora": "TIM", "tecnologia": "5G", "municipio": "Ananindeua", "lat": -1.336583, "lon": -48.384603, "data": "27/09/2005", "nova": false}, {"operadora": "Vivo", "tecnologia": "3G", "municipio": "Ananindeua", "lat": -1.336419, "lon": -48.403369, "data": "14/06/2021", "nova": false}, {"operadora": "Vivo", "tecnologia": "4G", "municipio": "Ananindeua", "lat": -1.336419, "lon": -48.403369, "data": "14/06/2021", "nova": false}, {"operadora": "Vivo", "tecnologia": "5G", "municipio": "Ananindeua", "lat": -1.336419, "lon": -48.403369, "data": "14/06/2021", "nova": false}, {"operadora": "Claro", "tecnologia": "3G", "municipio": "Ananindeua", "lat": -1.33601, "lon": -48.40127, "data": "08/11/2022", "nova": false}, {"operadora": "Claro", "tecnologia": "2G", "municipio": "Ananindeua", "lat": -1.33601, "lon": -48.40127, "data": "08/11/2022", "nova": false}, {"operadora": "Claro", "tecnologia": "4G", "municipio": "Ananindeua", "lat": -1.33601, "lon": -48.40127, "data": "08/11/2022", "nova": false}, {"operadora": "Claro", "tecnologia": "5G", "municipio": "Ananindeua", "lat": -1.33601, "lon": -48.40127, "data": "08/11/2022", "nova": false}, {"operadora": "TIM", "tecnologia": "4G", "municipio": "Ananindeua", "lat": -1.335833, "lon": -48.401111, "data": "29/03/2011", "nova": false}, {"operadora": "TIM", "tecnologia": "2G", "municipio": "Ananindeua", "lat": -1.335833, "lon": -48.401111, "data": "29/03/2011", "nova": false}, {"operadora": "TIM", "tecnologia": "3G", "municipio": "Ananindeua", "lat": -1.335833, "lon": -48.401111, "data": "29/03/2011", "nova": false}, {"operadora": "TIM", "tecnologia": "5G", "municipio": "Ananindeua", "lat": -1.335833, "lon": -48.401111, "data": "29/03/2011", "nova": false}, {"operadora": "TIM", "tecnologia": "4G", "municipio": "Ananindeua", "lat": -1.33472, "lon": -48.41778, "data": "20/02/2020", "nova": false}, {"operadora": "TIM", "tecnologia": "2G", "municipio": "Belém", "lat": -1.334639, "lon": -48.448306, "data": "18/09/2002", "nova": false}, {"operadora": "TIM", "tecnologia": "4G", "municipio": "Belém", "lat": -1.334639, "lon": -48.448306, "data": "18/09/2002", "nova": false}, {"operadora": "TIM", "tecnologia": "3G", "municipio": "Belém", "lat": -1.334639, "lon": -48.448306, "data": "18/09/2002", "nova": false}, {"operadora": "TIM", "tecnologia": "5G", "municipio": "Belém", "lat": -1.334639, "lon": -48.448306, "data": "18/09/2002", "nova": false}, {"operadora": "TIM", "tecnologia": "3G", "municipio": "Belém", "lat": -1.33444, "lon": -48.43778, "data": "17/10/2016", "nova": false}, {"operadora": "TIM", "tecnologia": "3G", "municipio": "Belém", "lat": -1.33417, "lon": -48.43667, "data": "17/10/2016", "nova": false}, {"operadora": "TIM", "tecnologia": "4G", "municipio": "Ananindeua", "lat": -1.33417, "lon": -48.38861, "data": "20/02/2020", "nova": false}, {"operadora": "TIM", "tecnologia": "4G", "municipio": "Ananindeua", "lat": -1.33417, "lon": -48.36028, "data": "17/06/2020", "nova": false}, {"operadora": "Vivo", "tecnologia": "5G", "municipio": "Ananindeua", "lat": -1.334083, "lon": -48.418444, "data": "18/12/2024", "nova": false}, {"operadora": "Claro", "tecnologia": "2G", "municipio": "Belém", "lat": -1.33389, "lon": -48.44833, "data": "08/07/2008", "nova": false}, {"operadora": "Claro", "tecnologia": "4G", "municipio": "Belém", "lat": -1.33389, "lon": -48.44833, "data": "08/07/2008", "nova": false}, {"operadora": "Claro", "tecnologia": "3G", "municipio": "Belém", "lat": -1.33389, "lon": -48.44833, "data": "08/07/2008", "nova": false}, {"operadora": "Claro", "tecnologia": "5G", "municipio": "Belém", "lat": -1.33389, "lon": -48.44833, "data": "08/07/2008", "nova": false}, {"operadora": "Claro", "tecnologia": "2G", "municipio": "Belém", "lat": -1.33388889, "lon": -48.44833333, "data": "24/10/2022", "nova": false}, {"operadora": "Vivo", "tecnologia": "3G", "municipio": "Ananindeua", "lat": -1.33333, "lon": -48.41167, "data": "11/08/2021", "nova": false}, {"operadora": "Vivo", "tecnologia": "2G", "municipio": "Ananindeua", "lat": -1.33333, "lon": -48.41167, "data": "11/08/2021", "nova": false}, {"operadora": "Vivo", "tecnologia": "4G", "municipio": "Ananindeua", "lat": -1.33333, "lon": -48.41167, "data": "11/08/2021", "nova": false}, {"operadora": "Vivo", "tecnologia": "5G", "municipio": "Ananindeua", "lat": -1.33333, "lon": -48.41167, "data": "11/08/2021", "nova": false}, {"operadora": "TIM", "tecnologia": "2G", "municipio": "Ananindeua", "lat": -1.333083, "lon": -48.411694, "data": "29/03/2011", "nova": false}, {"operadora": "TIM", "tecnologia": "5G", "municipio": "Ananindeua", "lat": -1.333083, "lon": -48.411694, "data": "29/03/2011", "nova": false}, {"operadora": "TIM", "tecnologia": "4G", "municipio": "Ananindeua", "lat": -1.333083, "lon": -48.411694, "data": "29/03/2011", "nova": false}, {"operadora": "TIM", "tecnologia": "3G", "municipio": "Ananindeua", "lat": -1.333083, "lon": -48.411694, "data": "29/03/2011", "nova": false}, {"operadora": "TIM", "tecnologia": "4G", "municipio": "Belém", "lat": -1.332194, "lon": -48.471806, "data": "20/08/2013", "nova": false}, {"operadora": "TIM", "tecnologia": "2G", "municipio": "Belém", "lat": -1.332194, "lon": -48.471806, "data": "20/08/2013", "nova": false}, {"operadora": "TIM", "tecnologia": "3G", "municipio": "Belém", "lat": -1.332194, "lon": -48.471806, "data": "20/08/2013", "nova": false}, {"operadora": "TIM", "tecnologia": "5G", "municipio": "Belém", "lat": -1.332194, "lon": -48.471806, "data": "20/08/2013", "nova": false}, {"operadora": "Claro", "tecnologia": "2G", "municipio": "Ananindeua", "lat": -1.331944, "lon": -48.416667, "data": "24/10/2022", "nova": false}, {"operadora": "Claro", "tecnologia": "3G", "municipio": "Ananindeua", "lat": -1.33194, "lon": -48.41666, "data": "21/05/2010", "nova": false}, {"operadora": "Claro", "tecnologia": "4G", "municipio": "Ananindeua", "lat": -1.33194, "lon": -48.41666, "data": "21/05/2010", "nova": false}, {"operadora": "Claro", "tecnologia": "2G", "municipio": "Ananindeua", "lat": -1.33194, "lon": -48.41666, "data": "21/05/2010", "nova": false}, {"operadora": "Claro", "tecnologia": "5G", "municipio": "Ananindeua", "lat": -1.33194, "lon": -48.41666, "data": "21/05/2010", "nova": false}, {"operadora": "TIM", "tecnologia": "4G", "municipio": "Ananindeua", "lat": -1.33194, "lon": -48.37833, "data": "20/11/2019", "nova": false}, {"operadora": "TIM", "tecnologia": "4G", "municipio": "Belém", "lat": -1.331583, "lon": -48.437, "data": "11/03/2019", "nova": false}, {"operadora": "TIM", "tecnologia": "5G", "municipio": "Belém", "lat": -1.331583, "lon": -48.437, "data": "11/03/2019", "nova": false}, {"operadora": "Vivo", "tecnologia": "5G", "municipio": "Ananindeua", "lat": -1.33126, "lon": -48.38943, "data": "16/12/2024", "nova": false}, {"operadora": "Vivo", "tecnologia": "4G", "municipio": "Ananindeua", "lat": -1.33126, "lon": -48.38943, "data": "16/12/2024", "nova": false}, {"operadora": "Vivo", "tecnologia": "5G", "municipio": "Belém", "lat": -1.331222, "lon": -48.436917, "data": "02/08/2011", "nova": false}, {"operadora": "Vivo", "tecnologia": "3G", "municipio": "Belém", "lat": -1.33111, "lon": -48.43667, "data": "02/08/2011", "nova": false}, {"operadora": "Vivo", "tecnologia": "2G", "municipio": "Belém", "lat": -1.33111, "lon": -48.43667, "data": "02/08/2011", "nova": false}, {"operadora": "Vivo", "tecnologia": "4G", "municipio": "Belém", "lat": -1.33111, "lon": -48.43667, "data": "02/08/2011", "nova": false}, {"operadora": "Vivo", "tecnologia": "4G", "municipio": "Belém", "lat": -1.330611, "lon": -48.447631, "data": "15/10/2024", "nova": false}, {"operadora": "Vivo", "tecnologia": "5G", "municipio": "Belém", "lat": -1.330611, "lon": -48.447631, "data": "15/10/2024", "nova": false}, {"operadora": "TIM", "tecnologia": "3G", "municipio": "Belém", "lat": -1.33056, "lon": -48.45278, "data": "17/10/2016", "nova": false}, {"operadora": "TIM", "tecnologia": "4G", "municipio": "Ananindeua", "lat": -1.330361, "lon": -48.3735, "data": "03/06/2011", "nova": false}, {"operadora": "TIM", "tecnologia": "2G", "municipio": "Ananindeua", "lat": -1.330361, "lon": -48.3735, "data": "03/06/2011", "nova": false}, {"operadora": "TIM", "tecnologia": "3G", "municipio": "Ananindeua", "lat": -1.330361, "lon": -48.3735, "data": "03/06/2011", "nova": false}, {"operadora": "TIM", "tecnologia": "5G", "municipio": "Ananindeua", "lat": -1.330361, "lon": -48.3735, "data": "03/06/2011", "nova": false}, {"operadora": "Vivo", "tecnologia": "3G", "municipio": "Belém", "lat": -1.33028, "lon": -48.47556, "data": "25/07/2008", "nova": false}, {"operadora": "Vivo", "tecnologia": "4G", "municipio": "Belém", "lat": -1.33028, "lon": -48.47556, "data": "25/07/2008", "nova": false}, {"operadora": "Vivo", "tecnologia": "5G", "municipio": "Belém", "lat": -1.33028, "lon": -48.47556, "data": "25/07/2008", "nova": false}, {"operadora": "Vivo", "tecnologia": "3G", "municipio": "Ananindeua", "lat": -1.33028, "lon": -48.37333, "data": "26/08/2014", "nova": false}, {"operadora": "Vivo", "tecnologia": "4G", "municipio": "Ananindeua", "lat": -1.33028, "lon": -48.37333, "data": "26/08/2014", "nova": false}, {"operadora": "Vivo", "tecnologia": "5G", "municipio": "Ananindeua", "lat": -1.33028, "lon": -48.37333, "data": "26/08/2014", "nova": false}, {"operadora": "Claro", "tecnologia": "2G", "municipio": "Belém", "lat": -1.330226, "lon": -48.475768, "data": "24/10/2022", "nova": false}, {"operadora": "Claro", "tecnologia": "4G", "municipio": "Belém", "lat": -1.33022, "lon": -48.47576, "data": "09/11/2021", "nova": false}, {"operadora": "Claro", "tecnologia": "2G", "municipio": "Belém", "lat": -1.33022, "lon": -48.47576, "data": "09/11/2021", "nova": false}, {"operadora": "Claro", "tecnologia": "3G", "municipio": "Belém", "lat": -1.33022, "lon": -48.47576, "data": "09/11/2021", "nova": false}, {"operadora": "Claro", "tecnologia": "5G", "municipio": "Belém", "lat": -1.33022, "lon": -48.47576, "data": "09/11/2021", "nova": false}, {"operadora": "TIM", "tecnologia": "4G", "municipio": "Belém", "lat": -1.330167, "lon": -48.475778, "data": "25/09/2015", "nova": false}, {"operadora": "TIM", "tecnologia": "3G", "municipio": "Belém", "lat": -1.330167, "lon": -48.475778, "data": "25/09/2015", "nova": false}, {"operadora": "TIM", "tecnologia": "5G", "municipio": "Belém", "lat": -1.330167, "lon": -48.475778, "data": "25/09/2015", "nova": false}, {"operadora": "TIM", "tecnologia": "3G", "municipio": "Belém", "lat": -1.330044, "lon": -48.450479, "data": "13/06/2023", "nova": false}, {"operadora": "TIM", "tecnologia": "4G", "municipio": "Belém", "lat": -1.330044, "lon": -48.450479, "data": "13/06/2023", "nova": false}, {"operadora": "TIM", "tecnologia": "3G", "municipio": "Belém", "lat": -1.32972, "lon": -48.43167, "data": "17/10/2016", "nova": false}, {"operadora": "TIM", "tecnologia": "4G", "municipio": "Ananindeua", "lat": -1.32972, "lon": -48.41694, "data": "20/02/2020", "nova": false}, {"operadora": "Vivo", "tecnologia": "3G", "municipio": "Ananindeua", "lat": -1.32966, "lon": -48.40072, "data": "18/11/2014", "nova": false}, {"operadora": "Vivo", "tecnologia": "4G", "municipio": "Ananindeua", "lat": -1.32966, "lon": -48.40072, "data": "18/11/2014", "nova": false}, {"operadora": "Vivo", "tecnologia": "5G", "municipio": "Ananindeua", "lat": -1.32966, "lon": -48.40072, "data": "18/11/2014", "nova": false}, {"operadora": "Claro", "tecnologia": "2G", "municipio": "Ananindeua", "lat": -1.3296, "lon": -48.40073, "data": "10/01/2018", "nova": false}, {"operadora": "Claro", "tecnologia": "3G", "municipio": "Ananindeua", "lat": -1.3296, "lon": -48.40073, "data": "10/01/2018", "nova": false}, {"operadora": "Claro", "tecnologia": "4G", "municipio": "Ananindeua", "lat": -1.3296, "lon": -48.40073, "data": "10/01/2018", "nova": false}, {"operadora": "Claro", "tecnologia": "5G", "municipio": "Ananindeua", "lat": -1.3296, "lon": -48.40073, "data": "10/01/2018", "nova": false}, {"operadora": "TIM", "tecnologia": "4G", "municipio": "Ananindeua", "lat": -1.329139, "lon": -48.402, "data": "11/11/2013", "nova": false}, {"operadora": "TIM", "tecnologia": "2G", "municipio": "Ananindeua", "lat": -1.329139, "lon": -48.402, "data": "11/11/2013", "nova": false}, {"operadora": "TIM", "tecnologia": "3G", "municipio": "Ananindeua", "lat": -1.329139, "lon": -48.402, "data": "11/11/2013", "nova": false}, {"operadora": "TIM", "tecnologia": "5G", "municipio": "Ananindeua", "lat": -1.329139, "lon": -48.402, "data": "11/11/2013", "nova": false}, {"operadora": "Claro", "tecnologia": "3G", "municipio": "Ananindeua", "lat": -1.32831, "lon": -48.37669, "data": "05/06/2018", "nova": false}, {"operadora": "Claro", "tecnologia": "4G", "municipio": "Ananindeua", "lat": -1.32831, "lon": -48.37669, "data": "05/06/2018", "nova": false}, {"operadora": "Claro", "tecnologia": "5G", "municipio": "Ananindeua", "lat": -1.32831, "lon": -48.37669, "data": "05/06/2018", "nova": false}, {"operadora": "TIM", "tecnologia": "4G", "municipio": "Belém", "lat": -1.328, "lon": -48.450417, "data": "25/06/2015", "nova": false}, {"operadora": "TIM", "tecnologia": "3G", "municipio": "Belém", "lat": -1.328, "lon": -48.450417, "data": "25/06/2015", "nova": false}, {"operadora": "TIM", "tecnologia": "5G", "municipio": "Belém", "lat": -1.328, "lon": -48.450417, "data": "25/06/2015", "nova": false}, {"operadora": "Claro", "tecnologia": "4G", "municipio": "Belém", "lat": -1.3279, "lon": -48.46499, "data": "28/11/2022", "nova": false}, {"operadora": "Claro", "tecnologia": "2G", "municipio": "Belém", "lat": -1.3279, "lon": -48.46499, "data": "28/11/2022", "nova": false}, {"operadora": "Claro", "tecnologia": "5G", "municipio": "Belém", "lat": -1.3279, "lon": -48.46499, "data": "28/11/2022", "nova": false}, {"operadora": "TIM", "tecnologia": "4G", "municipio": "Belém", "lat": -1.327806, "lon": -48.465028, "data": "29/03/2011", "nova": false}, {"operadora": "TIM", "tecnologia": "2G", "municipio": "Belém", "lat": -1.327806, "lon": -48.465028, "data": "29/03/2011", "nova": false}, {"operadora": "TIM", "tecnologia": "3G", "municipio": "Belém", "lat": -1.327806, "lon": -48.465028, "data": "29/03/2011", "nova": false}, {"operadora": "TIM", "tecnologia": "5G", "municipio": "Belém", "lat": -1.327806, "lon": -48.465028, "data": "29/03/2011", "nova": false}, {"operadora": "TIM", "tecnologia": "4G", "municipio": "Belém", "lat": -1.326056, "lon": -48.438833, "data": "18/09/2002", "nova": false}, {"operadora": "TIM", "tecnologia": "2G", "municipio": "Belém", "lat": -1.326056, "lon": -48.438833, "data": "18/09/2002", "nova": false}, {"operadora": "TIM", "tecnologia": "5G", "municipio": "Belém", "lat": -1.326056, "lon": -48.438833, "data": "18/09/2002", "nova": false}, {"operadora": "TIM", "tecnologia": "3G", "municipio": "Belém", "lat": -1.326056, "lon": -48.438833, "data": "18/09/2002", "nova": false}, {"operadora": "Vivo", "tecnologia": "3G", "municipio": "Belém", "lat": -1.32605, "lon": -48.43895, "data": "26/08/2014", "nova": false}, {"operadora": "Vivo", "tecnologia": "4G", "municipio": "Belém", "lat": -1.32605, "lon": -48.43895, "data": "26/08/2014", "nova": false}, {"operadora": "Vivo", "tecnologia": "5G", "municipio": "Belém", "lat": -1.32605, "lon": -48.43895, "data": "26/08/2014", "nova": false}, {"operadora": "Claro", "tecnologia": "3G", "municipio": "Belém", "lat": -1.32599, "lon": -48.43853, "data": "08/07/2008", "nova": false}, {"operadora": "Claro", "tecnologia": "2G", "municipio": "Belém", "lat": -1.32599, "lon": -48.43853, "data": "08/07/2008", "nova": false}, {"operadora": "Claro", "tecnologia": "4G", "municipio": "Belém", "lat": -1.32599, "lon": -48.43853, "data": "08/07/2008", "nova": false}, {"operadora": "Claro", "tecnologia": "5G", "municipio": "Belém", "lat": -1.32599, "lon": -48.43853, "data": "08/07/2008", "nova": false}, {"operadora": "TIM", "tecnologia": "3G", "municipio": "Belém", "lat": -1.32556, "lon": -48.42972, "data": "06/11/2016", "nova": false}, {"operadora": "TIM", "tecnologia": "4G", "municipio": "Ananindeua", "lat": -1.32528, "lon": -48.41556, "data": "26/08/2019", "nova": false}, {"operadora": "TIM", "tecnologia": "5G", "municipio": "Ananindeua", "lat": -1.32528, "lon": -48.41556, "data": "26/08/2019", "nova": false}, {"operadora": "Claro", "tecnologia": "5G", "municipio": "Ananindeua", "lat": -1.3251, "lon": -48.35232, "data": "08/07/2024", "nova": false}, {"operadora": "Claro", "tecnologia": "4G", "municipio": "Ananindeua", "lat": -1.3251, "lon": -48.35232, "data": "08/07/2024", "nova": false}, {"operadora": "Claro", "tecnologia": "3G", "municipio": "Ananindeua", "lat": -1.3251, "lon": -48.35232, "data": "08/07/2024", "nova": false}, {"operadora": "Vivo", "tecnologia": "4G", "municipio": "Belém", "lat": -1.325, "lon": -48.4325, "data": "10/06/2024", "nova": false}, {"operadora": "Vivo", "tecnologia": "5G", "municipio": "Belém", "lat": -1.325, "lon": -48.4325, "data": "10/06/2024", "nova": false}, {"operadora": "TIM", "tecnologia": "4G", "municipio": "Ananindeua", "lat": -1.325, "lon": -48.37611, "data": "23/05/2019", "nova": false}, {"operadora": "TIM", "tecnologia": "5G", "municipio": "Ananindeua", "lat": -1.325, "lon": -48.37611, "data": "23/05/2019", "nova": false}, {"operadora": "Vivo", "tecnologia": "3G", "municipio": "Ananindeua", "lat": -1.32472, "lon": -48.35194, "data": "04/11/2002", "nova": false}, {"operadora": "Vivo", "tecnologia": "2G", "municipio": "Ananindeua", "lat": -1.32472, "lon": -48.35194, "data": "04/11/2002", "nova": false}, {"operadora": "Vivo", "tecnologia": "4G", "municipio": "Ananindeua", "lat": -1.32472, "lon": -48.35194, "data": "04/11/2002", "nova": false}, {"operadora": "Vivo", "tecnologia": "5G", "municipio": "Ananindeua", "lat": -1.32472, "lon": -48.35194, "data": "04/11/2002", "nova": false}, {"operadora": "Vivo", "tecnologia": "5G", "municipio": "Ananindeua", "lat": -1.324173, "lon": -48.400079, "data": "07/03/2025", "nova": false}, {"operadora": "TIM", "tecnologia": "4G", "municipio": "Belém", "lat": -1.323889, "lon": -48.450278, "data": "29/03/2011", "nova": false}, {"operadora": "TIM", "tecnologia": "3G", "municipio": "Belém", "lat": -1.323889, "lon": -48.450278, "data": "29/03/2011", "nova": false}, {"operadora": "TIM", "tecnologia": "2G", "municipio": "Belém", "lat": -1.323889, "lon": -48.450278, "data": "29/03/2011", "nova": false}, {"operadora": "TIM", "tecnologia": "5G", "municipio": "Belém", "lat": -1.323889, "lon": -48.450278, "data": "29/03/2011", "nova": false}, {"operadora": "Claro", "tecnologia": "4G", "municipio": "Ananindeua", "lat": -1.3238, "lon": -48.40013, "data": "04/12/2024", "nova": false}, {"operadora": "Claro", "tecnologia": "5G", "municipio": "Ananindeua", "lat": -1.3238, "lon": -48.40013, "data": "04/12/2024", "nova": false}, {"operadora": "Claro", "tecnologia": "3G", "municipio": "Belém", "lat": -1.32375, "lon": -48.46711, "data": "23/03/2018", "nova": false}, {"operadora": "Claro", "tecnologia": "4G", "municipio": "Belém", "lat": -1.32375, "lon": -48.46711, "data": "23/03/2018", "nova": false}, {"operadora": "Claro", "tecnologia": "5G", "municipio": "Belém", "lat": -1.32375, "lon": -48.46711, "data": "23/03/2018", "nova": false}, {"operadora": "Claro", "tecnologia": "4G", "municipio": "Ananindeua", "lat": -1.32313, "lon": -48.41881, "data": "16/10/2024", "nova": false}, {"operadora": "Claro", "tecnologia": "5G", "municipio": "Ananindeua", "lat": -1.32313, "lon": -48.41881, "data": "16/10/2024", "nova": false}, {"operadora": "Claro", "tecnologia": "4G", "municipio": "Ananindeua", "lat": -1.32311, "lon": -48.38802, "data": "11/10/2024", "nova": false}, {"operadora": "Claro", "tecnologia": "5G", "municipio": "Ananindeua", "lat": -1.32311, "lon": -48.38802, "data": "11/10/2024", "nova": false}, {"operadora": "Claro", "tecnologia": "3G", "municipio": "Ananindeua", "lat": -1.32311, "lon": -48.38802, "data": "11/10/2024", "nova": false}, {"operadora": "Vivo", "tecnologia": "3G", "municipio": "Ananindeua", "lat": -1.322967, "lon": -48.418833, "data": "14/12/2020", "nova": false}, {"operadora": "Vivo", "tecnologia": "5G", "municipio": "Ananindeua", "lat": -1.322967, "lon": -48.418833, "data": "14/12/2020", "nova": false}, {"operadora": "Vivo", "tecnologia": "4G", "municipio": "Ananindeua", "lat": -1.322967, "lon": -48.418833, "data": "14/12/2020", "nova": false}, {"operadora": "Claro", "tecnologia": "3G", "municipio": "Belém", "lat": -1.32213, "lon": -48.4547, "data": "20/03/2009", "nova": false}, {"operadora": "Claro", "tecnologia": "4G", "municipio": "Belém", "lat": -1.32213, "lon": -48.4547, "data": "20/03/2009", "nova": false}, {"operadora": "Claro", "tecnologia": "5G", "municipio": "Belém", "lat": -1.32213, "lon": -48.4547, "data": "20/03/2009", "nova": false}, {"operadora": "Vivo", "tecnologia": "3G", "municipio": "Belém", "lat": -1.32194, "lon": -48.45444, "data": "15/01/2013", "nova": false}, {"operadora": "Vivo", "tecnologia": "2G", "municipio": "Belém", "lat": -1.32194, "lon": -48.45444, "data": "15/01/2013", "nova": false}, {"operadora": "Vivo", "tecnologia": "4G", "municipio": "Belém", "lat": -1.32194, "lon": -48.45444, "data": "15/01/2013", "nova": false}, {"operadora": "Vivo", "tecnologia": "5G", "municipio": "Belém", "lat": -1.32194, "lon": -48.45444, "data": "15/01/2013", "nova": false}, {"operadora": "TIM", "tecnologia": "2G", "municipio": "Belém", "lat": -1.321842, "lon": -48.438164, "data": "25/10/2024", "nova": false}, {"operadora": "TIM", "tecnologia": "4G", "municipio": "Belém", "lat": -1.321842, "lon": -48.438164, "data": "25/10/2024", "nova": false}, {"operadora": "TIM", "tecnologia": "3G", "municipio": "Belém", "lat": -1.321842, "lon": -48.438164, "data": "25/10/2024", "nova": false}, {"operadora": "TIM", "tecnologia": "5G", "municipio": "Belém", "lat": -1.321842, "lon": -48.438164, "data": "25/10/2024", "nova": false}, {"operadora": "Claro", "tecnologia": "4G", "municipio": "Ananindeua", "lat": -1.32124, "lon": -48.40974, "data": "18/09/2024", "nova": false}, {"operadora": "Claro", "tecnologia": "5G", "municipio": "Ananindeua", "lat": -1.32124, "lon": -48.40974, "data": "18/09/2024", "nova": false}, {"operadora": "Claro", "tecnologia": "3G", "municipio": "Ananindeua", "lat": -1.32124, "lon": -48.40974, "data": "18/09/2024", "nova": false}, {"operadora": "Vivo", "tecnologia": "5G", "municipio": "Ananindeua", "lat": -1.320583, "lon": -48.40081, "data": "18/03/2025", "nova": false}, {"operadora": "Claro", "tecnologia": "4G", "municipio": "Ananindeua", "lat": -1.32053, "lon": -48.40096, "data": "04/12/2024", "nova": false}, {"operadora": "Claro", "tecnologia": "5G", "municipio": "Ananindeua", "lat": -1.32053, "lon": -48.40096, "data": "04/12/2024", "nova": false}, {"operadora": "Claro", "tecnologia": "3G", "municipio": "Ananindeua", "lat": -1.32053, "lon": -48.40096, "data": "04/12/2024", "nova": false}, {"operadora": "Vivo", "tecnologia": "3G", "municipio": "Belém", "lat": -1.320331, "lon": -48.434719, "data": "26/04/2012", "nova": false}, {"operadora": "Vivo", "tecnologia": "4G", "municipio": "Belém", "lat": -1.320331, "lon": -48.434719, "data": "26/04/2012", "nova": false}, {"operadora": "Vivo", "tecnologia": "2G", "municipio": "Belém", "lat": -1.320331, "lon": -48.434719, "data": "26/04/2012", "nova": false}, {"operadora": "Vivo", "tecnologia": "5G", "municipio": "Belém", "lat": -1.320331, "lon": -48.434719, "data": "26/04/2012", "nova": false}, {"operadora": "Vivo", "tecnologia": "4G", "municipio": "Belém", "lat": -1.31942, "lon": -48.4437, "data": "15/02/2022", "nova": false}, {"operadora": "Vivo", "tecnologia": "5G", "municipio": "Belém", "lat": -1.31942, "lon": -48.4437, "data": "15/02/2022", "nova": false}, {"operadora": "Claro", "tecnologia": "3G", "municipio": "Ananindeua", "lat": -1.3179, "lon": -48.40126, "data": "16/12/2024", "nova": false}, {"operadora": "Claro", "tecnologia": "4G", "municipio": "Ananindeua", "lat": -1.3179, "lon": -48.40126, "data": "16/12/2024", "nova": false}, {"operadora": "Claro", "tecnologia": "5G", "municipio": "Ananindeua", "lat": -1.3179, "lon": -48.40126, "data": "16/12/2024", "nova": false}, {"operadora": "Claro", "tecnologia": "3G", "municipio": "Belém", "lat": -1.31772, "lon": -48.43746, "data": "10/06/2022", "nova": false}, {"operadora": "Claro", "tecnologia": "4G", "municipio": "Belém", "lat": -1.31772, "lon": -48.43746, "data": "10/06/2022", "nova": false}, {"operadora": "Claro", "tecnologia": "5G", "municipio": "Belém", "lat": -1.31772, "lon": -48.43746, "data": "10/06/2022", "nova": false}, {"operadora": "TIM", "tecnologia": "4G", "municipio": "Belém", "lat": -1.317694, "lon": -48.436972, "data": "11/11/2013", "nova": false}, {"operadora": "TIM", "tecnologia": "2G", "municipio": "Belém", "lat": -1.317694, "lon": -48.436972, "data": "11/11/2013", "nova": false}, {"operadora": "TIM", "tecnologia": "3G", "municipio": "Belém", "lat": -1.317694, "lon": -48.436972, "data": "11/11/2013", "nova": false}, {"operadora": "TIM", "tecnologia": "5G", "municipio": "Belém", "lat": -1.317694, "lon": -48.436972, "data": "11/11/2013", "nova": false}, {"operadora": "TIM", "tecnologia": "4G", "municipio": "Belém", "lat": -1.314167, "lon": -48.462806, "data": "05/11/2010", "nova": false}, {"operadora": "TIM", "tecnologia": "2G", "municipio": "Belém", "lat": -1.314167, "lon": -48.462806, "data": "05/11/2010", "nova": false}, {"operadora": "TIM", "tecnologia": "3G", "municipio": "Belém", "lat": -1.314167, "lon": -48.462806, "data": "05/11/2010", "nova": false}, {"operadora": "TIM", "tecnologia": "5G", "municipio": "Belém", "lat": -1.314167, "lon": -48.462806, "data": "05/11/2010", "nova": false}, {"operadora": "Claro", "tecnologia": "4G", "municipio": "Belém", "lat": -1.31411, "lon": -48.463, "data": "08/07/2024", "nova": false}, {"operadora": "Claro", "tecnologia": "5G", "municipio": "Belém", "lat": -1.31411, "lon": -48.463, "data": "08/07/2024", "nova": false}, {"operadora": "TIM", "tecnologia": "4G", "municipio": "Belém", "lat": -1.313722, "lon": -48.472889, "data": "26/03/2020", "nova": false}, {"operadora": "Vivo", "tecnologia": "3G", "municipio": "Belém", "lat": -1.313389, "lon": -48.458694, "data": "08/09/2021", "nova": false}, {"operadora": "Vivo", "tecnologia": "2G", "municipio": "Belém", "lat": -1.313389, "lon": -48.458694, "data": "08/09/2021", "nova": false}, {"operadora": "Vivo", "tecnologia": "4G", "municipio": "Belém", "lat": -1.313389, "lon": -48.458694, "data": "08/09/2021", "nova": false}, {"operadora": "Vivo", "tecnologia": "5G", "municipio": "Belém", "lat": -1.313389, "lon": -48.458694, "data": "08/09/2021", "nova": false}, {"operadora": "Claro", "tecnologia": "2G", "municipio": "Belém", "lat": -1.31251, "lon": -48.45086, "data": "08/07/2008", "nova": false}, {"operadora": "Claro", "tecnologia": "4G", "municipio": "Belém", "lat": -1.31251, "lon": -48.45086, "data": "08/07/2008", "nova": false}, {"operadora": "Claro", "tecnologia": "3G", "municipio": "Belém", "lat": -1.31251, "lon": -48.45086, "data": "08/07/2008", "nova": false}, {"operadora": "Claro", "tecnologia": "5G", "municipio": "Belém", "lat": -1.31251, "lon": -48.45086, "data": "08/07/2008", "nova": false}, {"operadora": "Vivo", "tecnologia": "3G", "municipio": "Belém", "lat": -1.3125, "lon": -48.4525, "data": "26/08/2014", "nova": false}, {"operadora": "Vivo", "tecnologia": "4G", "municipio": "Belém", "lat": -1.3125, "lon": -48.4525, "data": "26/08/2014", "nova": false}, {"operadora": "Vivo", "tecnologia": "5G", "municipio": "Belém", "lat": -1.3125, "lon": -48.4525, "data": "26/08/2014", "nova": false}, {"operadora": "TIM", "tecnologia": "4G", "municipio": "Belém", "lat": -1.312361, "lon": -48.450278, "data": "18/09/2002", "nova": false}, {"operadora": "TIM", "tecnologia": "2G", "municipio": "Belém", "lat": -1.312361, "lon": -48.450278, "data": "18/09/2002", "nova": false}, {"operadora": "TIM", "tecnologia": "3G", "municipio": "Belém", "lat": -1.312361, "lon": -48.450278, "data": "18/09/2002", "nova": false}, {"operadora": "TIM", "tecnologia": "5G", "municipio": "Belém", "lat": -1.312361, "lon": -48.450278, "data": "18/09/2002", "nova": false}, {"operadora": "Claro", "tecnologia": "2G", "municipio": "Belém", "lat": -1.312222, "lon": -48.450833, "data": "24/10/2022", "nova": false}, {"operadora": "Vivo", "tecnologia": "3G", "municipio": "Belém", "lat": -1.310647, "lon": -48.474817, "data": "02/08/2011", "nova": false}, {"operadora": "Vivo", "tecnologia": "2G", "municipio": "Belém", "lat": -1.310647, "lon": -48.474817, "data": "02/08/2011", "nova": false}, {"operadora": "Vivo", "tecnologia": "4G", "municipio": "Belém", "lat": -1.310647, "lon": -48.474817, "data": "02/08/2011", "nova": false}, {"operadora": "Vivo", "tecnologia": "5G", "municipio": "Belém", "lat": -1.310647, "lon": -48.474817, "data": "02/08/2011", "nova": false}, {"operadora": "Claro", "tecnologia": "2G", "municipio": "Belém", "lat": -1.310322, "lon": -48.474389, "data": "24/10/2022", "nova": false}, {"operadora": "Claro", "tecnologia": "2G", "municipio": "Belém", "lat": -1.31032, "lon": -48.47439, "data": "08/07/2008", "nova": false}, {"operadora": "Claro", "tecnologia": "3G", "municipio": "Belém", "lat": -1.31032, "lon": -48.47439, "data": "08/07/2008", "nova": false}, {"operadora": "Claro", "tecnologia": "4G", "municipio": "Belém", "lat": -1.31032, "lon": -48.47439, "data": "08/07/2008", "nova": false}, {"operadora": "Claro", "tecnologia": "5G", "municipio": "Belém", "lat": -1.31032, "lon": -48.47439, "data": "08/07/2008", "nova": false}, {"operadora": "TIM", "tecnologia": "4G", "municipio": "Belém", "lat": -1.309972, "lon": -48.475111, "data": "18/09/2002", "nova": false}, {"operadora": "TIM", "tecnologia": "3G", "municipio": "Belém", "lat": -1.309972, "lon": -48.475111, "data": "18/09/2002", "nova": false}, {"operadora": "TIM", "tecnologia": "2G", "municipio": "Belém", "lat": -1.309972, "lon": -48.475111, "data": "18/09/2002", "nova": false}, {"operadora": "TIM", "tecnologia": "5G", "municipio": "Belém", "lat": -1.309972, "lon": -48.475111, "data": "18/09/2002", "nova": false}, {"operadora": "TIM", "tecnologia": "2G", "municipio": "Belém", "lat": -1.308472, "lon": -48.467611, "data": "08/04/2013", "nova": false}, {"operadora": "TIM", "tecnologia": "4G", "municipio": "Belém", "lat": -1.308472, "lon": -48.467611, "data": "08/04/2013", "nova": false}, {"operadora": "TIM", "tecnologia": "3G", "municipio": "Belém", "lat": -1.308472, "lon": -48.467611, "data": "08/04/2013", "nova": false}, {"operadora": "TIM", "tecnologia": "5G", "municipio": "Belém", "lat": -1.308472, "lon": -48.467611, "data": "08/04/2013", "nova": false}, {"operadora": "Vivo", "tecnologia": "4G", "municipio": "Belém", "lat": -1.305794, "lon": -48.460831, "data": "12/07/2021", "nova": false}, {"operadora": "Claro", "tecnologia": "3G", "municipio": "Belém", "lat": -1.30576, "lon": -48.46088, "data": "03/10/2022", "nova": false}, {"operadora": "Claro", "tecnologia": "2G", "municipio": "Belém", "lat": -1.30576, "lon": -48.46088, "data": "03/10/2022", "nova": false}, {"operadora": "Claro", "tecnologia": "4G", "municipio": "Belém", "lat": -1.30576, "lon": -48.46088, "data": "03/10/2022", "nova": false}, {"operadora": "Claro", "tecnologia": "5G", "municipio": "Belém", "lat": -1.30576, "lon": -48.46088, "data": "03/10/2022", "nova": false}, {"operadora": "Vivo", "tecnologia": "3G", "municipio": "Belém", "lat": -1.30556, "lon": -48.46167, "data": "12/07/2021", "nova": false}, {"operadora": "Vivo", "tecnologia": "4G", "municipio": "Belém", "lat": -1.30556, "lon": -48.46167, "data": "12/07/2021", "nova": false}, {"operadora": "Vivo", "tecnologia": "5G", "municipio": "Belém", "lat": -1.30556, "lon": -48.46167, "data": "12/07/2021", "nova": false}, {"operadora": "TIM", "tecnologia": "4G", "municipio": "Belém", "lat": -1.30389, "lon": -48.47861, "data": "26/03/2020", "nova": false}, {"operadora": "TIM", "tecnologia": "5G", "municipio": "Belém", "lat": -1.30389, "lon": -48.47861, "data": "26/03/2020", "nova": false}, {"operadora": "Claro", "tecnologia": "3G", "municipio": "Belém", "lat": -1.30383, "lon": -48.47067, "data": "09/08/2010", "nova": false}, {"operadora": "Claro", "tecnologia": "4G", "municipio": "Belém", "lat": -1.30383, "lon": -48.47067, "data": "09/08/2010", "nova": false}, {"operadora": "Claro", "tecnologia": "2G", "municipio": "Belém", "lat": -1.30383, "lon": -48.47067, "data": "09/08/2010", "nova": false}, {"operadora": "Claro", "tecnologia": "5G", "municipio": "Belém", "lat": -1.30383, "lon": -48.47067, "data": "09/08/2010", "nova": false}, {"operadora": "TIM", "tecnologia": "3G", "municipio": "Belém", "lat": -1.303083, "lon": -48.45725, "data": "29/03/2011", "nova": false}, {"operadora": "TIM", "tecnologia": "2G", "municipio": "Belém", "lat": -1.303083, "lon": -48.45725, "data": "29/03/2011", "nova": false}, {"operadora": "TIM", "tecnologia": "4G", "municipio": "Belém", "lat": -1.303083, "lon": -48.45725, "data": "29/03/2011", "nova": false}, {"operadora": "TIM", "tecnologia": "5G", "municipio": "Belém", "lat": -1.303083, "lon": -48.45725, "data": "29/03/2011", "nova": false}, {"operadora": "TIM", "tecnologia": "4G", "municipio": "Belém", "lat": -1.301944, "lon": -48.470639, "data": "28/05/2008", "nova": false}, {"operadora": "TIM", "tecnologia": "3G", "municipio": "Belém", "lat": -1.301944, "lon": -48.470639, "data": "28/05/2008", "nova": false}, {"operadora": "TIM", "tecnologia": "2G", "municipio": "Belém", "lat": -1.301944, "lon": -48.470639, "data": "28/05/2008", "nova": false}, {"operadora": "TIM", "tecnologia": "5G", "municipio": "Belém", "lat": -1.301944, "lon": -48.470639, "data": "28/05/2008", "nova": false}, {"operadora": "TIM", "tecnologia": "3G", "municipio": "Belém", "lat": -1.30056, "lon": -48.46972, "data": "17/10/2016", "nova": false}, {"operadora": "TIM", "tecnologia": "4G", "municipio": "Belém", "lat": -1.300389, "lon": -48.466, "data": "17/07/2015", "nova": false}, {"operadora": "TIM", "tecnologia": "3G", "municipio": "Belém", "lat": -1.300389, "lon": -48.466, "data": "17/07/2015", "nova": false}, {"operadora": "TIM", "tecnologia": "5G", "municipio": "Belém", "lat": -1.300389, "lon": -48.466, "data": "17/07/2015", "nova": false}, {"operadora": "Claro", "tecnologia": "2G", "municipio": "Belém", "lat": -1.300278, "lon": -48.465833, "data": "24/10/2022", "nova": false}, {"operadora": "Claro", "tecnologia": "4G", "municipio": "Belém", "lat": -1.30027, "lon": -48.46583, "data": "09/11/2021", "nova": false}, {"operadora": "Claro", "tecnologia": "2G", "municipio": "Belém", "lat": -1.30027, "lon": -48.46583, "data": "09/11/2021", "nova": false}, {"operadora": "Claro", "tecnologia": "3G", "municipio": "Belém", "lat": -1.30027, "lon": -48.46583, "data": "09/11/2021", "nova": false}, {"operadora": "Claro", "tecnologia": "5G", "municipio": "Belém", "lat": -1.30027, "lon": -48.46583, "data": "09/11/2021", "nova": false}, {"operadora": "Vivo", "tecnologia": "5G", "municipio": "Belém", "lat": -1.29963, "lon": -48.45219, "data": "15/10/2024", "nova": false}, {"operadora": "Vivo", "tecnologia": "4G", "municipio": "Belém", "lat": -1.29963, "lon": -48.45219, "data": "15/10/2024", "nova": false}, {"operadora": "Claro", "tecnologia": "3G", "municipio": "Belém", "lat": -1.29945, "lon": -48.48069, "data": "10/06/2022", "nova": false}, {"operadora": "Claro", "tecnologia": "4G", "municipio": "Belém", "lat": -1.29945, "lon": -48.48069, "data": "10/06/2022", "nova": false}, {"operadora": "Claro", "tecnologia": "5G", "municipio": "Belém", "lat": -1.29945, "lon": -48.48069, "data": "10/06/2022", "nova": false}, {"operadora": "Vivo", "tecnologia": "3G", "municipio": "Belém", "lat": -1.29833, "lon": -48.47861, "data": "08/10/1999", "nova": false}, {"operadora": "Vivo", "tecnologia": "4G", "municipio": "Belém", "lat": -1.29833, "lon": -48.47861, "data": "08/10/1999", "nova": false}, {"operadora": "Vivo", "tecnologia": "2G", "municipio": "Belém", "lat": -1.29833, "lon": -48.47861, "data": "08/10/1999", "nova": false}, {"operadora": "Vivo", "tecnologia": "5G", "municipio": "Belém", "lat": -1.29833, "lon": -48.47861, "data": "08/10/1999", "nova": false}, {"operadora": "Vivo", "tecnologia": "3G", "municipio": "Belém", "lat": -1.29806, "lon": -48.47056, "data": "14/06/2021", "nova": false}, {"operadora": "Vivo", "tecnologia": "4G", "municipio": "Belém", "lat": -1.29806, "lon": -48.47056, "data": "14/06/2021", "nova": false}, {"operadora": "Vivo", "tecnologia": "5G", "municipio": "Belém", "lat": -1.29806, "lon": -48.47056, "data": "14/06/2021", "nova": false}, {"operadora": "TIM", "tecnologia": "4G", "municipio": "Belém", "lat": -1.296139, "lon": -48.480139, "data": "20/11/2012", "nova": false}, {"operadora": "TIM", "tecnologia": "3G", "municipio": "Belém", "lat": -1.296139, "lon": -48.480139, "data": "20/11/2012", "nova": false}, {"operadora": "TIM", "tecnologia": "2G", "municipio": "Belém", "lat": -1.296139, "lon": -48.480139, "data": "20/11/2012", "nova": false}, {"operadora": "TIM", "tecnologia": "5G", "municipio": "Belém", "lat": -1.296139, "lon": -48.480139, "data": "20/11/2012", "nova": false}, {"operadora": "TIM", "tecnologia": "4G", "municipio": "Belém", "lat": -1.295881, "lon": -48.475564, "data": "15/05/2024", "nova": false}, {"operadora": "Claro", "tecnologia": "5G", "municipio": "Belém", "lat": -1.2945, "lon": -48.437, "data": "17/10/2024", "nova": false}, {"operadora": "Claro", "tecnologia": "4G", "municipio": "Belém", "lat": -1.2945, "lon": -48.437, "data": "17/10/2024", "nova": false}, {"operadora": "Claro", "tecnologia": "3G", "municipio": "Belém", "lat": -1.2945, "lon": -48.437, "data": "17/10/2024", "nova": false}, {"operadora": "Vivo", "tecnologia": "4G", "municipio": "Belém", "lat": -1.294231, "lon": -48.434369, "data": "08/12/2021", "nova": false}, {"operadora": "TIM", "tecnologia": "4G", "municipio": "Belém", "lat": -1.294231, "lon": -48.434369, "data": "28/11/2022", "nova": false}, {"operadora": "Vivo", "tecnologia": "5G", "municipio": "Belém", "lat": -1.294231, "lon": -48.434369, "data": "08/12/2021", "nova": false}, {"operadora": "Claro", "tecnologia": "3G", "municipio": "Belém", "lat": -1.29364, "lon": -48.46883, "data": "17/05/2018", "nova": false}, {"operadora": "Claro", "tecnologia": "4G", "municipio": "Belém", "lat": -1.29364, "lon": -48.46883, "data": "17/05/2018", "nova": false}, {"operadora": "Claro", "tecnologia": "5G", "municipio": "Belém", "lat": -1.29364, "lon": -48.46883, "data": "17/05/2018", "nova": false}, {"operadora": "Claro", "tecnologia": "3G", "municipio": "Belém", "lat": -1.29248, "lon": -48.47995, "data": "09/11/2021", "nova": false}, {"operadora": "Claro", "tecnologia": "4G", "municipio": "Belém", "lat": -1.29248, "lon": -48.47995, "data": "09/11/2021", "nova": false}, {"operadora": "Claro", "tecnologia": "5G", "municipio": "Belém", "lat": -1.29248, "lon": -48.47995, "data": "09/11/2021", "nova": false}, {"operadora": "Vivo", "tecnologia": "4G", "municipio": "Belém", "lat": -1.29248, "lon": -48.47995, "data": "13/01/2026", "nova": true}, {"operadora": "Vivo", "tecnologia": "5G", "municipio": "Belém", "lat": -1.29248, "lon": -48.47995, "data": "13/01/2026", "nova": true}, {"operadora": "Claro", "tecnologia": "2G", "municipio": "Belém", "lat": -1.29165, "lon": -48.4529, "data": "08/07/2008", "nova": false}, {"operadora": "Claro", "tecnologia": "3G", "municipio": "Belém", "lat": -1.29165, "lon": -48.4529, "data": "08/07/2008", "nova": false}, {"operadora": "Claro", "tecnologia": "4G", "municipio": "Belém", "lat": -1.29165, "lon": -48.4529, "data": "08/07/2008", "nova": false}, {"operadora": "Claro", "tecnologia": "5G", "municipio": "Belém", "lat": -1.29165, "lon": -48.4529, "data": "08/07/2008", "nova": false}, {"operadora": "TIM", "tecnologia": "4G", "municipio": "Belém", "lat": -1.291056, "lon": -48.457472, "data": "18/09/2002", "nova": false}, {"operadora": "TIM", "tecnologia": "2G", "municipio": "Belém", "lat": -1.291056, "lon": -48.457472, "data": "18/09/2002", "nova": false}, {"operadora": "TIM", "tecnologia": "3G", "municipio": "Belém", "lat": -1.291056, "lon": -48.457472, "data": "18/09/2002", "nova": false}, {"operadora": "TIM", "tecnologia": "5G", "municipio": "Belém", "lat": -1.291056, "lon": -48.457472, "data": "18/09/2002", "nova": false}, {"operadora": "Vivo", "tecnologia": "5G", "municipio": "Belém", "lat": -1.291056, "lon": -48.457472, "data": "08/09/2021", "nova": false}, {"operadora": "Vivo", "tecnologia": "3G", "municipio": "Belém", "lat": -1.29083, "lon": -48.45722, "data": "08/09/2021", "nova": false}, {"operadora": "Vivo", "tecnologia": "2G", "municipio": "Belém", "lat": -1.29083, "lon": -48.45722, "data": "08/09/2021", "nova": false}, {"operadora": "Vivo", "tecnologia": "4G", "municipio": "Belém", "lat": -1.29083, "lon": -48.45722, "data": "08/09/2021", "nova": false}, {"operadora": "Vivo", "tecnologia": "4G", "municipio": "Belém", "lat": -1.2842, "lon": -48.45825, "data": "11/07/2025", "nova": true}, {"operadora": "Claro", "tecnologia": "3G", "municipio": "Belém", "lat": -1.28416, "lon": -48.45825, "data": "05/11/2021", "nova": false}, {"operadora": "Claro", "tecnologia": "4G", "municipio": "Belém", "lat": -1.28416, "lon": -48.45825, "data": "05/11/2021", "nova": false}, {"operadora": "Claro", "tecnologia": "5G", "municipio": "Belém", "lat": -1.28416, "lon": -48.45825, "data": "05/11/2021", "nova": false}, {"operadora": "TIM", "tecnologia": "4G", "municipio": "Belém", "lat": -1.282833, "lon": -48.468139, "data": "15/05/2024", "nova": false}, {"operadora": "Vivo", "tecnologia": "4G", "municipio": "Belém", "lat": -1.278192, "lon": -48.480003, "data": "30/10/2025", "nova": true}, {"operadora": "Vivo", "tecnologia": "5G", "municipio": "Belém", "lat": -1.278192, "lon": -48.480003, "data": "30/10/2025", "nova": true}, {"operadora": "Claro", "tecnologia": "2G", "municipio": "Belém", "lat": -1.27745, "lon": -48.47397, "data": "24/10/2022", "nova": false}, {"operadora": "Claro", "tecnologia": "2G", "municipio": "Belém", "lat": -1.27741, "lon": -48.47403, "data": "12/06/2008", "nova": false}, {"operadora": "Claro", "tecnologia": "4G", "municipio": "Belém", "lat": -1.27741, "lon": -48.47403, "data": "12/06/2008", "nova": false}, {"operadora": "Claro", "tecnologia": "3G", "municipio": "Belém", "lat": -1.27741, "lon": -48.47403, "data": "12/06/2008", "nova": false}, {"operadora": "Claro", "tecnologia": "5G", "municipio": "Belém", "lat": -1.27741, "lon": -48.47403, "data": "12/06/2008", "nova": false}, {"operadora": "Vivo", "tecnologia": "4G", "municipio": "Belém", "lat": -1.2774, "lon": -48.474038, "data": "11/07/2025", "nova": true}, {"operadora": "Vivo", "tecnologia": "5G", "municipio": "Belém", "lat": -1.2774, "lon": -48.474038, "data": "11/07/2025", "nova": true}, {"operadora": "TIM", "tecnologia": "4G", "municipio": "Belém", "lat": -1.27722, "lon": -48.47389, "data": "17/12/2002", "nova": false}, {"operadora": "TIM", "tecnologia": "2G", "municipio": "Belém", "lat": -1.27722, "lon": -48.47389, "data": "17/12/2002", "nova": false}, {"operadora": "TIM", "tecnologia": "3G", "municipio": "Belém", "lat": -1.27722, "lon": -48.47389, "data": "17/12/2002", "nova": false}, {"operadora": "TIM", "tecnologia": "5G", "municipio": "Belém", "lat": -1.27722, "lon": -48.47389, "data": "17/12/2002", "nova": false}, {"operadora": "Vivo", "tecnologia": "4G", "municipio": "Belém", "lat": -1.275575, "lon": -48.481006, "data": "30/10/2025", "nova": true}, {"operadora": "Vivo", "tecnologia": "5G", "municipio": "Belém", "lat": -1.275575, "lon": -48.481006, "data": "30/10/2025", "nova": true}, {"operadora": "Vivo", "tecnologia": "3G", "municipio": "Belém", "lat": -1.27, "lon": -48.43778, "data": "02/08/2011", "nova": false}, {"operadora": "Vivo", "tecnologia": "4G", "municipio": "Belém", "lat": -1.27, "lon": -48.43778, "data": "02/08/2011", "nova": false}, {"operadora": "Vivo", "tecnologia": "5G", "municipio": "Belém", "lat": -1.27, "lon": -48.43778, "data": "02/08/2011", "nova": false}, {"operadora": "TIM", "tecnologia": "4G", "municipio": "Belém", "lat": -1.26917, "lon": -48.43694, "data": "12/06/2015", "nova": false}, {"operadora": "TIM", "tecnologia": "3G", "municipio": "Belém", "lat": -1.26917, "lon": -48.43694, "data": "12/06/2015", "nova": false}, {"operadora": "TIM", "tecnologia": "5G", "municipio": "Belém", "lat": -1.26917, "lon": -48.43694, "data": "12/06/2015", "nova": false}, {"operadora": "Vivo", "tecnologia": "3G", "municipio": "Belém", "lat": -1.266526, "lon": -48.472468, "data": "14/12/2020", "nova": false}, {"operadora": "Vivo", "tecnologia": "5G", "municipio": "Belém", "lat": -1.266526, "lon": -48.472468, "data": "14/12/2020", "nova": false}, {"operadora": "Vivo", "tecnologia": "4G", "municipio": "Belém", "lat": -1.266526, "lon": -48.472468, "data": "14/12/2020", "nova": false}, {"operadora": "TIM", "tecnologia": "3G", "municipio": "Belém", "lat": -1.266525, "lon": -48.472467, "data": "11/07/2011", "nova": false}, {"operadora": "TIM", "tecnologia": "2G", "municipio": "Belém", "lat": -1.266525, "lon": -48.472467, "data": "11/07/2011", "nova": false}, {"operadora": "TIM", "tecnologia": "4G", "municipio": "Belém", "lat": -1.266525, "lon": -48.472467, "data": "11/07/2011", "nova": false}, {"operadora": "TIM", "tecnologia": "5G", "municipio": "Belém", "lat": -1.266525, "lon": -48.472467, "data": "11/07/2011", "nova": false}, {"operadora": "TIM", "tecnologia": "4G", "municipio": "Belém", "lat": -1.265583, "lon": -48.452139, "data": "10/07/2015", "nova": false}, {"operadora": "TIM", "tecnologia": "3G", "municipio": "Belém", "lat": -1.265583, "lon": -48.452139, "data": "10/07/2015", "nova": false}, {"operadora": "TIM", "tecnologia": "5G", "municipio": "Belém", "lat": -1.265583, "lon": -48.452139, "data": "10/07/2015", "nova": false}, {"operadora": "Claro", "tecnologia": "3G", "municipio": "Belém", "lat": -1.26557, "lon": -48.45211, "data": "08/11/2022", "nova": false}, {"operadora": "Claro", "tecnologia": "4G", "municipio": "Belém", "lat": -1.26557, "lon": -48.45211, "data": "08/11/2022", "nova": false}, {"operadora": "Claro", "tecnologia": "2G", "municipio": "Belém", "lat": -1.26557, "lon": -48.45211, "data": "08/11/2022", "nova": false}, {"operadora": "Claro", "tecnologia": "5G", "municipio": "Belém", "lat": -1.26557, "lon": -48.45211, "data": "08/11/2022", "nova": false}, {"operadora": "Vivo", "tecnologia": "4G", "municipio": "Belém", "lat": -1.2652, "lon": -48.439667, "data": "11/07/2025", "nova": true}, {"operadora": "Claro", "tecnologia": "2G", "municipio": "Belém", "lat": -1.26516, "lon": -48.43966, "data": "30/04/2018", "nova": false}, {"operadora": "Claro", "tecnologia": "3G", "municipio": "Belém", "lat": -1.26516, "lon": -48.43966, "data": "30/04/2018", "nova": false}, {"operadora": "Claro", "tecnologia": "4G", "municipio": "Belém", "lat": -1.26516, "lon": -48.43966, "data": "30/04/2018", "nova": false}, {"operadora": "Claro", "tecnologia": "5G", "municipio": "Belém", "lat": -1.26516, "lon": -48.43966, "data": "30/04/2018", "nova": false}, {"operadora": "Claro", "tecnologia": "2G", "municipio": "Belém", "lat": -1.25996, "lon": -48.4657, "data": "08/07/2008", "nova": false}, {"operadora": "Claro", "tecnologia": "3G", "municipio": "Belém", "lat": -1.25996, "lon": -48.4657, "data": "08/07/2008", "nova": false}, {"operadora": "Claro", "tecnologia": "4G", "municipio": "Belém", "lat": -1.25996, "lon": -48.4657, "data": "08/07/2008", "nova": false}, {"operadora": "Claro", "tecnologia": "5G", "municipio": "Belém", "lat": -1.25996, "lon": -48.4657, "data": "08/07/2008", "nova": false}, {"operadora": "Claro", "tecnologia": "2G", "municipio": "Belém", "lat": -1.25988, "lon": -48.46579, "data": "24/10/2022", "nova": false}, {"operadora": "TIM", "tecnologia": "2G", "municipio": "Belém", "lat": -1.259444, "lon": -48.465, "data": "17/12/2002", "nova": false}, {"operadora": "TIM", "tecnologia": "4G", "municipio": "Belém", "lat": -1.259444, "lon": -48.465, "data": "17/12/2002", "nova": false}, {"operadora": "TIM", "tecnologia": "3G", "municipio": "Belém", "lat": -1.259444, "lon": -48.465, "data": "17/12/2002", "nova": false}, {"operadora": "TIM", "tecnologia": "5G", "municipio": "Belém", "lat": -1.259444, "lon": -48.465, "data": "17/12/2002", "nova": false}, {"operadora": "Claro", "tecnologia": "2G", "municipio": "Belém", "lat": -1.259083, "lon": -48.452611, "data": "24/10/2022", "nova": false}, {"operadora": "Claro", "tecnologia": "3G", "municipio": "Belém", "lat": -1.25908, "lon": -48.45261, "data": "06/02/2013", "nova": false}, {"operadora": "Claro", "tecnologia": "2G", "municipio": "Belém", "lat": -1.25908, "lon": -48.45261, "data": "06/02/2013", "nova": false}, {"operadora": "Claro", "tecnologia": "4G", "municipio": "Belém", "lat": -1.25908, "lon": -48.45261, "data": "06/02/2013", "nova": false}, {"operadora": "Claro", "tecnologia": "5G", "municipio": "Belém", "lat": -1.25908, "lon": -48.45261, "data": "06/02/2013", "nova": false}, {"operadora": "Vivo", "tecnologia": "3G", "municipio": "Belém", "lat": -1.25889, "lon": -48.4525, "data": "26/08/2014", "nova": false}, {"operadora": "Vivo", "tecnologia": "4G", "municipio": "Belém", "lat": -1.25889, "lon": -48.4525, "data": "26/08/2014", "nova": false}, {"operadora": "Vivo", "tecnologia": "5G", "municipio": "Belém", "lat": -1.25889, "lon": -48.4525, "data": "26/08/2014", "nova": false}, {"operadora": "TIM", "tecnologia": "2G", "municipio": "Belém", "lat": -1.253639, "lon": -48.454722, "data": "03/06/2011", "nova": false}, {"operadora": "TIM", "tecnologia": "4G", "municipio": "Belém", "lat": -1.253639, "lon": -48.454722, "data": "03/06/2011", "nova": false}, {"operadora": "TIM", "tecnologia": "3G", "municipio": "Belém", "lat": -1.253639, "lon": -48.454722, "data": "03/06/2011", "nova": false}, {"operadora": "TIM", "tecnologia": "5G", "municipio": "Belém", "lat": -1.253639, "lon": -48.454722, "data": "03/06/2011", "nova": false}, {"operadora": "Vivo", "tecnologia": "3G", "municipio": "Belém", "lat": -1.253333, "lon": -48.460278, "data": "08/10/1999", "nova": false}, {"operadora": "Vivo", "tecnologia": "2G", "municipio": "Belém", "lat": -1.253333, "lon": -48.460278, "data": "08/10/1999", "nova": false}, {"operadora": "Vivo", "tecnologia": "4G", "municipio": "Belém", "lat": -1.253333, "lon": -48.460278, "data": "08/10/1999", "nova": false}, {"operadora": "Vivo", "tecnologia": "5G", "municipio": "Belém", "lat": -1.253333, "lon": -48.460278, "data": "08/10/1999", "nova": false}, {"operadora": "Claro", "tecnologia": "3G", "municipio": "Belém", "lat": -1.2492, "lon": -48.45315, "data": "05/11/2021", "nova": false}, {"operadora": "Claro", "tecnologia": "4G", "municipio": "Belém", "lat": -1.2492, "lon": -48.45315, "data": "05/11/2021", "nova": false}, {"operadora": "Claro", "tecnologia": "2G", "municipio": "Belém", "lat": -1.2492, "lon": -48.45315, "data": "05/11/2021", "nova": false}, {"operadora": "Claro", "tecnologia": "5G", "municipio": "Belém", "lat": -1.2492, "lon": -48.45315, "data": "05/11/2021", "nova": false}, {"operadora": "TIM", "tecnologia": "4G", "municipio": "Belém", "lat": -1.2423, "lon": -48.450281, "data": "19/03/2020", "nova": false}, {"operadora": "Vivo", "tecnologia": "2G", "municipio": "Belém", "lat": -1.16417, "lon": -48.47083, "data": "08/09/2021", "nova": false}, {"operadora": "Vivo", "tecnologia": "3G", "municipio": "Belém", "lat": -1.16417, "lon": -48.47083, "data": "08/09/2021", "nova": false}, {"operadora": "Vivo", "tecnologia": "4G", "municipio": "Belém", "lat": -1.16417, "lon": -48.47083, "data": "08/09/2021", "nova": false}, {"operadora": "Vivo", "tecnologia": "5G", "municipio": "Belém", "lat": -1.164167, "lon": -48.470833, "data": "08/09/2021", "nova": false}, {"operadora": "TIM", "tecnologia": "4G", "municipio": "Belém", "lat": -1.1639, "lon": -48.4719, "data": "30/06/2025", "nova": true}, {"operadora": "TIM", "tecnologia": "3G", "municipio": "Belém", "lat": -1.162111, "lon": -48.467, "data": "17/12/2002", "nova": false}, {"operadora": "TIM", "tecnologia": "4G", "municipio": "Belém", "lat": -1.162111, "lon": -48.467, "data": "17/12/2002", "nova": false}, {"operadora": "TIM", "tecnologia": "2G", "municipio": "Belém", "lat": -1.162111, "lon": -48.467, "data": "17/12/2002", "nova": false}, {"operadora": "TIM", "tecnologia": "5G", "municipio": "Belém", "lat": -1.162111, "lon": -48.467, "data": "17/12/2002", "nova": false}, {"operadora": "Claro", "tecnologia": "2G", "municipio": "Belém", "lat": -1.1618, "lon": -48.46738, "data": "08/07/2008", "nova": false}, {"operadora": "Claro", "tecnologia": "3G", "municipio": "Belém", "lat": -1.1618, "lon": -48.46738, "data": "08/07/2008", "nova": false}, {"operadora": "Claro", "tecnologia": "4G", "municipio": "Belém", "lat": -1.1618, "lon": -48.46738, "data": "08/07/2008", "nova": false}, {"operadora": "Claro", "tecnologia": "5G", "municipio": "Belém", "lat": -1.1618, "lon": -48.46738, "data": "08/07/2008", "nova": false}, {"operadora": "Vivo", "tecnologia": "4G", "municipio": "Belém", "lat": -1.15343, "lon": -48.46927, "data": "14/01/2019", "nova": false}, {"operadora": "Vivo", "tecnologia": "3G", "municipio": "Belém", "lat": -1.15343, "lon": -48.46927, "data": "14/01/2019", "nova": false}, {"operadora": "Claro", "tecnologia": "4G", "municipio": "Belém", "lat": -1.1531, "lon": -48.46891, "data": "25/09/2025", "nova": true}, {"operadora": "Claro", "tecnologia": "5G", "municipio": "Belém", "lat": -1.1531, "lon": -48.46891, "data": "25/09/2025", "nova": true}, {"operadora": "TIM", "tecnologia": "4G", "municipio": "Belém", "lat": -1.153056, "lon": -48.468889, "data": "29/03/2011", "nova": false}, {"operadora": "TIM", "tecnologia": "2G", "municipio": "Belém", "lat": -1.153056, "lon": -48.468889, "data": "29/03/2011", "nova": false}, {"operadora": "TIM", "tecnologia": "3G", "municipio": "Belém", "lat": -1.153056, "lon": -48.468889, "data": "29/03/2011", "nova": false}, {"operadora": "TIM", "tecnologia": "5G", "municipio": "Belém", "lat": -1.153056, "lon": -48.468889, "data": "29/03/2011", "nova": false}, {"operadora": "Vivo", "tecnologia": "5G", "municipio": "Belém", "lat": -1.153047, "lon": -48.468875, "data": "14/01/2019", "nova": false}, {"operadora": "Claro", "tecnologia": "3G", "municipio": "Belém", "lat": -1.14291, "lon": -48.45995, "data": "09/11/2021", "nova": false}, {"operadora": "Claro", "tecnologia": "2G", "municipio": "Belém", "lat": -1.14291, "lon": -48.45995, "data": "09/11/2021", "nova": false}, {"operadora": "Claro", "tecnologia": "4G", "municipio": "Belém", "lat": -1.14291, "lon": -48.45995, "data": "09/11/2021", "nova": false}, {"operadora": "Claro", "tecnologia": "5G", "municipio": "Belém", "lat": -1.14291, "lon": -48.45995, "data": "09/11/2021", "nova": false}, {"operadora": "Claro", "tecnologia": "2G", "municipio": "Belém", "lat": -1.142778, "lon": -48.459722, "data": "24/10/2022", "nova": false}, {"operadora": "Claro", "tecnologia": "2G", "municipio": "Belém", "lat": -1.14193, "lon": -48.46243, "data": "07/11/2022", "nova": false}, {"operadora": "Claro", "tecnologia": "4G", "municipio": "Belém", "lat": -1.14193, "lon": -48.46243, "data": "07/11/2022", "nova": false}, {"operadora": "Claro", "tecnologia": "3G", "municipio": "Belém", "lat": -1.14193, "lon": -48.46243, "data": "07/11/2022", "nova": false}, {"operadora": "Claro", "tecnologia": "5G", "municipio": "Belém", "lat": -1.14193, "lon": -48.46243, "data": "07/11/2022", "nova": false}, {"operadora": "TIM", "tecnologia": "3G", "municipio": "Belém", "lat": -1.141806, "lon": -48.462389, "data": "17/12/2002", "nova": false}, {"operadora": "TIM", "tecnologia": "5G", "municipio": "Belém", "lat": -1.141806, "lon": -48.462389, "data": "17/12/2002", "nova": false}, {"operadora": "TIM", "tecnologia": "4G", "municipio": "Belém", "lat": -1.141806, "lon": -48.462389, "data": "17/12/2002", "nova": false}, {"operadora": "TIM", "tecnologia": "2G", "municipio": "Belém", "lat": -1.141806, "lon": -48.462389, "data": "17/12/2002", "nova": false}, {"operadora": "TIM", "tecnologia": "2G", "municipio": "Belém", "lat": -1.1418, "lon": -48.462381, "data": "29/11/2024", "nova": false}, {"operadora": "TIM", "tecnologia": "4G", "municipio": "Belém", "lat": -1.1418, "lon": -48.462381, "data": "29/11/2024", "nova": false}, {"operadora": "TIM", "tecnologia": "3G", "municipio": "Belém", "lat": -1.1418, "lon": -48.462381, "data": "29/11/2024", "nova": false}, {"operadora": "TIM", "tecnologia": "4G", "municipio": "Belém", "lat": -1.137083, "lon": -48.451583, "data": "08/07/2015", "nova": false}, {"operadora": "TIM", "tecnologia": "3G", "municipio": "Belém", "lat": -1.137083, "lon": -48.451583, "data": "08/07/2015", "nova": false}, {"operadora": "TIM", "tecnologia": "5G", "municipio": "Belém", "lat": -1.137083, "lon": -48.451583, "data": "08/07/2015", "nova": false}, {"operadora": "Claro", "tecnologia": "4G", "municipio": "Belém", "lat": -1.13707, "lon": -48.45159, "data": "29/07/2025", "nova": true}, {"operadora": "TIM", "tecnologia": "4G", "municipio": "Belém", "lat": -1.128389, "lon": -48.4465, "data": "13/12/2010", "nova": false}, {"operadora": "TIM", "tecnologia": "2G", "municipio": "Belém", "lat": -1.128389, "lon": -48.4465, "data": "13/12/2010", "nova": false}, {"operadora": "TIM", "tecnologia": "3G", "municipio": "Belém", "lat": -1.128389, "lon": -48.4465, "data": "13/12/2010", "nova": false}, {"operadora": "TIM", "tecnologia": "5G", "municipio": "Belém", "lat": -1.128389, "lon": -48.4465, "data": "13/12/2010", "nova": false}, {"operadora": "Vivo", "tecnologia": "3G", "municipio": "Belém", "lat": -1.12806, "lon": -48.44639, "data": "15/01/2013", "nova": false}, {"operadora": "Vivo", "tecnologia": "2G", "municipio": "Belém", "lat": -1.12806, "lon": -48.44639, "data": "15/01/2013", "nova": false}, {"operadora": "Vivo", "tecnologia": "4G", "municipio": "Belém", "lat": -1.12806, "lon": -48.44639, "data": "15/01/2013", "nova": false}, {"operadora": "Vivo", "tecnologia": "5G", "municipio": "Belém", "lat": -1.12806, "lon": -48.44639, "data": "15/01/2013", "nova": false}, {"operadora": "Claro", "tecnologia": "3G", "municipio": "Belém", "lat": -1.12687, "lon": -48.44576, "data": "25/04/2018", "nova": false}, {"operadora": "Claro", "tecnologia": "4G", "municipio": "Belém", "lat": -1.12687, "lon": -48.44576, "data": "25/04/2018", "nova": false}, {"operadora": "Claro", "tecnologia": "2G", "municipio": "Belém", "lat": -1.12687, "lon": -48.44576, "data": "25/04/2018", "nova": false}, {"operadora": "Claro", "tecnologia": "5G", "municipio": "Belém", "lat": -1.12687, "lon": -48.44576, "data": "25/04/2018", "nova": false}, {"operadora": "TIM", "tecnologia": "4G", "municipio": "Belém", "lat": -1.121194, "lon": -48.4295, "data": "17/12/2002", "nova": false}, {"operadora": "TIM", "tecnologia": "2G", "municipio": "Belém", "lat": -1.121194, "lon": -48.4295, "data": "17/12/2002", "nova": false}, {"operadora": "TIM", "tecnologia": "3G", "municipio": "Belém", "lat": -1.121194, "lon": -48.4295, "data": "17/12/2002", "nova": false}, {"operadora": "TIM", "tecnologia": "5G", "municipio": "Belém", "lat": -1.121194, "lon": -48.4295, "data": "17/12/2002", "nova": false}, {"operadora": "Vivo", "tecnologia": "3G", "municipio": "Belém", "lat": -1.12111, "lon": -48.42917, "data": "30/09/2008", "nova": false}, {"operadora": "Vivo", "tecnologia": "2G", "municipio": "Belém", "lat": -1.12111, "lon": -48.42917, "data": "30/09/2008", "nova": false}, {"operadora": "Vivo", "tecnologia": "4G", "municipio": "Belém", "lat": -1.12111, "lon": -48.42917, "data": "30/09/2008", "nova": false}, {"operadora": "Vivo", "tecnologia": "5G", "municipio": "Belém", "lat": -1.12111, "lon": -48.42917, "data": "30/09/2008", "nova": false}, {"operadora": "TIM", "tecnologia": "4G", "municipio": "Belém", "lat": -1.1211, "lon": -48.4417, "data": "30/06/2025", "nova": true}, {"operadora": "Claro", "tecnologia": "2G", "municipio": "Belém", "lat": -1.12079, "lon": -48.42847, "data": "08/07/2008", "nova": false}, {"operadora": "Claro", "tecnologia": "3G", "municipio": "Belém", "lat": -1.12079, "lon": -48.42847, "data": "08/07/2008", "nova": false}, {"operadora": "Claro", "tecnologia": "4G", "municipio": "Belém", "lat": -1.12079, "lon": -48.42847, "data": "08/07/2008", "nova": false}, {"operadora": "Claro", "tecnologia": "5G", "municipio": "Belém", "lat": -1.12079, "lon": -48.42847, "data": "08/07/2008", "nova": false}, {"operadora": "Claro", "tecnologia": "4G", "municipio": "Belém", "lat": -1.10891, "lon": -48.42738, "data": "26/12/2022", "nova": false}, {"operadora": "Claro", "tecnologia": "2G", "municipio": "Belém", "lat": -1.10891, "lon": -48.42738, "data": "26/12/2022", "nova": false}, {"operadora": "Claro", "tecnologia": "5G", "municipio": "Belém", "lat": -1.10891, "lon": -48.42738, "data": "26/12/2022", "nova": false}, {"operadora": "TIM", "tecnologia": "4G", "municipio": "Belém", "lat": -1.107806, "lon": -48.417528, "data": "13/12/2010", "nova": false}, {"operadora": "TIM", "tecnologia": "2G", "municipio": "Belém", "lat": -1.107806, "lon": -48.417528, "data": "13/12/2010", "nova": false}, {"operadora": "TIM", "tecnologia": "3G", "municipio": "Belém", "lat": -1.107806, "lon": -48.417528, "data": "13/12/2010", "nova": false}, {"operadora": "TIM", "tecnologia": "5G", "municipio": "Belém", "lat": -1.107806, "lon": -48.417528, "data": "13/12/2010", "nova": false}, {"operadora": "Vivo", "tecnologia": "3G", "municipio": "Belém", "lat": -1.107425, "lon": -48.417644, "data": "05/04/2019", "nova": false}, {"operadora": "Vivo", "tecnologia": "4G", "municipio": "Belém", "lat": -1.107425, "lon": -48.417644, "data": "05/04/2019", "nova": false}, {"operadora": "Vivo", "tecnologia": "5G", "municipio": "Belém", "lat": -1.107425, "lon": -48.417644, "data": "05/04/2019", "nova": false}, {"operadora": "Vivo", "tecnologia": "5G", "municipio": "Belém", "lat": -1.102781, "lon": -48.40195, "data": "08/10/1999", "nova": false}, {"operadora": "Vivo", "tecnologia": "3G", "municipio": "Belém", "lat": -1.10278, "lon": -48.40194, "data": "08/10/1999", "nova": false}, {"operadora": "Vivo", "tecnologia": "2G", "municipio": "Belém", "lat": -1.10278, "lon": -48.40194, "data": "08/10/1999", "nova": false}, {"operadora": "Vivo", "tecnologia": "4G", "municipio": "Belém", "lat": -1.10278, "lon": -48.40194, "data": "08/10/1999", "nova": false}, {"operadora": "Claro", "tecnologia": "3G", "municipio": "Belém", "lat": -1.10055, "lon": -48.40083, "data": "29/07/2008", "nova": false}, {"operadora": "Claro", "tecnologia": "2G", "municipio": "Belém", "lat": -1.10055, "lon": -48.40083, "data": "29/07/2008", "nova": false}, {"operadora": "Claro", "tecnologia": "4G", "municipio": "Belém", "lat": -1.10055, "lon": -48.40083, "data": "29/07/2008", "nova": false}, {"operadora": "Claro", "tecnologia": "5G", "municipio": "Belém", "lat": -1.10055, "lon": -48.40083, "data": "29/07/2008", "nova": false}, {"operadora": "TIM", "tecnologia": "4G", "municipio": "Belém", "lat": -1.097681, "lon": -48.406119, "data": "08/06/2011", "nova": false}, {"operadora": "TIM", "tecnologia": "2G", "municipio": "Belém", "lat": -1.097681, "lon": -48.406119, "data": "08/06/2011", "nova": false}, {"operadora": "TIM", "tecnologia": "3G", "municipio": "Belém", "lat": -1.097681, "lon": -48.406119, "data": "08/06/2011", "nova": false}, {"operadora": "TIM", "tecnologia": "5G", "municipio": "Belém", "lat": -1.097681, "lon": -48.406119, "data": "08/06/2011", "nova": false}, {"operadora": "Claro", "tecnologia": "4G", "municipio": "Belém", "lat": -1.09764, "lon": -48.40619, "data": "04/11/2022", "nova": false}, {"operadora": "Claro", "tecnologia": "3G", "municipio": "Belém", "lat": -1.09764, "lon": -48.40619, "data": "04/11/2022", "nova": false}, {"operadora": "Claro", "tecnologia": "2G", "municipio": "Belém", "lat": -1.09764, "lon": -48.40619, "data": "04/11/2022", "nova": false}, {"operadora": "Claro", "tecnologia": "5G", "municipio": "Belém", "lat": -1.09764, "lon": -48.40619, "data": "04/11/2022", "nova": false}, {"operadora": "Claro", "tecnologia": "4G", "municipio": "Belém", "lat": -1.07239, "lon": -48.39222, "data": "28/11/2022", "nova": false}, {"operadora": "Claro", "tecnologia": "2G", "municipio": "Belém", "lat": -1.07239, "lon": -48.39222, "data": "28/11/2022", "nova": false}, {"operadora": "Claro", "tecnologia": "5G", "municipio": "Belém", "lat": -1.07239, "lon": -48.39222, "data": "28/11/2022", "nova": false}, {"operadora": "Vivo", "tecnologia": "5G", "municipio": "Belém", "lat": -1.071111, "lon": -48.352778, "data": "02/09/2021", "nova": false}, {"operadora": "Vivo", "tecnologia": "4G", "municipio": "Belém", "lat": -1.071111, "lon": -48.352778, "data": "02/09/2021", "nova": false}, {"operadora": "Vivo", "tecnologia": "2G", "municipio": "Belém", "lat": -1.071111, "lon": -48.352778, "data": "02/09/2021", "nova": false}, {"operadora": "Vivo", "tecnologia": "3G", "municipio": "Belém", "lat": -1.071111, "lon": -48.352778, "data": "02/09/2021", "nova": false}, {"operadora": "TIM", "tecnologia": "4G", "municipio": "Belém", "lat": -1.070667, "lon": -48.392361, "data": "20/02/2004", "nova": false}, {"operadora": "TIM", "tecnologia": "2G", "municipio": "Belém", "lat": -1.070667, "lon": -48.392361, "data": "20/02/2004", "nova": false}, {"operadora": "TIM", "tecnologia": "3G", "municipio": "Belém", "lat": -1.070667, "lon": -48.392361, "data": "20/02/2004", "nova": false}, {"operadora": "Claro", "tecnologia": "2G", "municipio": "Belém", "lat": -1.07008, "lon": -48.39219, "data": "08/07/2008", "nova": false}, {"operadora": "Claro", "tecnologia": "4G", "municipio": "Belém", "lat": -1.07008, "lon": -48.39219, "data": "08/07/2008", "nova": false}, {"operadora": "Claro", "tecnologia": "3G", "municipio": "Belém", "lat": -1.07008, "lon": -48.39219, "data": "08/07/2008", "nova": false}, {"operadora": "Claro", "tecnologia": "5G", "municipio": "Belém", "lat": -1.07008, "lon": -48.39219, "data": "08/07/2008", "nova": false}, {"operadora": "Vivo", "tecnologia": "3G", "municipio": "Belém", "lat": -1.07, "lon": -48.39194, "data": "06/12/2012", "nova": false}, {"operadora": "Vivo", "tecnologia": "2G", "municipio": "Belém", "lat": -1.07, "lon": -48.39194, "data": "06/12/2012", "nova": false}, {"operadora": "Vivo", "tecnologia": "4G", "municipio": "Belém", "lat": -1.07, "lon": -48.39194, "data": "06/12/2012", "nova": false}, {"operadora": "Vivo", "tecnologia": "5G", "municipio": "Belém", "lat": -1.07, "lon": -48.39194, "data": "06/12/2012", "nova": false}, {"operadora": "Vivo", "tecnologia": "4G", "municipio": "Belém", "lat": -1.06874, "lon": -48.38017, "data": "07/05/2024", "nova": false}, {"operadora": "Vivo", "tecnologia": "5G", "municipio": "Belém", "lat": -1.068739, "lon": -48.380169, "data": "07/05/2024", "nova": false}, {"operadora": "TIM", "tecnologia": "4G", "municipio": "Belém", "lat": -1.0686, "lon": -48.3803, "data": "30/06/2025", "nova": true}, {"operadora": "Claro", "tecnologia": "2G", "municipio": "Belém", "lat": -1.065972, "lon": -48.33766, "data": "24/10/2022", "nova": false}, {"operadora": "Claro", "tecnologia": "2G", "municipio": "Belém", "lat": -1.06597, "lon": -48.33766, "data": "09/11/2021", "nova": false}, {"operadora": "Claro", "tecnologia": "3G", "municipio": "Belém", "lat": -1.06597, "lon": -48.33766, "data": "09/11/2021", "nova": false}, {"operadora": "Claro", "tecnologia": "4G", "municipio": "Belém", "lat": -1.06597, "lon": -48.33766, "data": "09/11/2021", "nova": false}, {"operadora": "Claro", "tecnologia": "5G", "municipio": "Belém", "lat": -1.06597, "lon": -48.33766, "data": "09/11/2021", "nova": false}]