[{"operadora": "Claro", "tecnologia": "2G", "municipio": "Palestina do Pará", "lat": -6.12091, "lon": -48.32833, "data": "29/07/2025", "nova": true}, {"operadora": "Claro", "tecnologia": "4G", "municipio": "Palestina do Pará", "lat": -6.12091, "lon": -48.32833, "data": "29/07/2025", "nova": true}, {"operadora": "TIM", "tecnologia": "4G", "municipio": "Palestina do Pará", "lat": -5.745861, "lon": -48.320472, "data": "29/03/2021", "nova": false}, {"operadora": "TIM", "tecnologia": "3G", "municipio": "Palestina do Pará", "lat": -5.745861, "lon": -48.320472, "data": "29/03/2021", "nova": false}, {"operadora": "Claro", "tecnologia": "3G", "municipio": "Palestina do Pará", "lat": -5.7445, "lon": -48.31617, "data": "26/10/2017", "nova": false}, {"operadora": "Vivo", "tecnologia": "3G", "municipio": "Palestina do Pará", "lat": -5.74444, "lon": -48.31611, "data": "27/02/2010", "nova": false}, {"operadora": "Vivo", "tecnologia": "2G", "municipio": "Palestina do Pará", "lat": -5.74444, "lon": -48.31611, "data": "27/02/2010", "nova": false}, {"operadora": "Vivo", "tecnologia": "4G", "municipio": "Palestina do Pará", "lat": -5.74444, "lon": -48.31611, "data": "27/02/2010", "nova": false}, {"operadora": "Vivo", "tecnologia": "4G", "municipio": "Palestina do Pará", "lat": -5.7054, "lon": -48.177564, "data": "05/05/2025", "nova": true}, {"operadora": "Claro", "tecnologia": "3G", "municipio": "Brejo Grande do Araguaia", "lat": -5.70161, "lon": -48.40472, "data": "26/10/2017", "nova": false}, {"operadora": "Vivo", "tecnologia": "3G", "municipio": "Brejo Grande do Araguaia", "lat": -5.70139, "lon": -48.40472, "data": "11/08/2021", "nova": false}, {"operadora": "Vivo", "tecnologia": "2G", "municipio": "Brejo Grande do Araguaia", "lat": -5.70139, "lon": -48.40472, "data": "11/08/2021", "nova": false}, {"operadora": "Vivo", "tecnologia": "4G", "municipio": "Brejo Grande do Araguaia", "lat": -5.70139, "lon": -48.40472, "data": "11/08/2021", "nova": false}, {"operadora": "TIM", "tecnologia": "4G", "municipio": "Brejo Grande do Araguaia", "lat": -5.7004444444444, "lon": -48.39925, "data": "16/07/2021", "nova": false}, {"operadora": "Claro", "tecnologia": "2G", "municipio": "Palestina do Pará", "lat": -5.6936, "lon": -48.19592, "data": "20/02/2026", "nova": true}, {"operadora": "Claro", "tecnologia": "4G", "municipio": "Palestina do Pará", "lat": -5.6936, "lon": -48.19592, "data": "20/02/2026", "nova": true}, {"operadora": "Vivo", "tecnologia": "4G", "municipio": "Brejo Grande do Araguaia", "lat": -5.62295, "lon": -48.33501, "data": "13/01/2026", "nova": true}, {"operadora": "Vivo", "tecnologia": "4G", "municipio": "Brejo Grande do Araguaia", "lat": -5.586231, "lon": -48.202161, "data": "05/02/2025", "nova": false}, {"operadora": "Vivo", "tecnologia": "3G", "municipio": "Abel Figueiredo", "lat": -4.95417, "lon": -48.41194, "data": "31/08/2001", "nova": false}, {"operadora": "Vivo", "tecnologia": "2G", "municipio": "Abel Figueiredo", "lat": -4.95417, "lon": -48.41194, "data": "31/08/2001", "nova": false}, {"operadora": "Vivo", "tecnologia": "4G", "municipio": "Abel Figueiredo", "lat": -4.95417, "lon": -48.41194, "data": "31/08/2001", "nova": false}, {"operadora": "Claro", "tecnologia": "3G", "municipio": "Abel Figueiredo", "lat": -4.95417, "lon": -48.41194, "data": "26/10/2017", "nova": false}, {"operadora": "TIM", "tecnologia": "4G", "municipio": "Abel Figueiredo", "lat": -4.9499611, "lon": -48.394988, "data": "28/03/2022", "nova": false}, {"operadora": "Claro", "tecnologia": "4G", "municipio": "Rondon do Pará", "lat": -4.78915, "lon": -48.07402, "data": "29/09/2025", "nova": true}, {"operadora": "Vivo", "tecnologia": "3G", "municipio": "Rondon do Pará", "lat": -4.78889, "lon": -48.07389, "data": "05/07/2021", "nova": false}, {"operadora": "Vivo", "tecnologia": "4G", "municipio": "Rondon do Pará", "lat": -4.78889, "lon": -48.07389, "data": "05/07/2021", "nova": false}, {"operadora": "Vivo", "tecnologia": "5G", "municipio": "Rondon do Pará", "lat": -4.78889, "lon": -48.07389, "data": "05/07/2021", "nova": false}, {"operadora": "Vivo", "tecnologia": "3G", "municipio": "Rondon do Pará", "lat": -4.786944, "lon": -48.065, "data": "19/01/2001", "nova": false}, {"operadora": "Vivo", "tecnologia": "4G", "municipio": "Rondon do Pará", "lat": -4.786944, "lon": -48.065, "data": "19/01/2001", "nova": false}, {"operadora": "Vivo", "tecnologia": "2G", "municipio": "Rondon do Pará", "lat": -4.786944, "lon": -48.065, "data": "19/01/2001", "nova": false}, {"operadora": "Vivo", "tecnologia": "5G", "municipio": "Rondon do Pará", "lat": -4.786944, "lon": -48.065, "data": "19/01/2001", "nova": false}, {"operadora": "Claro", "tecnologia": "4G", "municipio": "Rondon do Pará", "lat": -4.78694, "lon": -48.065, "data": "02/02/2026", "nova": true}, {"operadora": "Claro", "tecnologia": "3G", "municipio": "Rondon do Pará", "lat": -4.78163, "lon": -48.07061, "data": "30/09/2008", "nova": false}, {"operadora": "Claro", "tecnologia": "2G", "municipio": "Rondon do Pará", "lat": -4.78163, "lon": -48.07061, "data": "30/09/2008", "nova": false}, {"operadora": "Claro", "tecnologia": "4G", "municipio": "Rondon do Pará", "lat": -4.78163, "lon": -48.07061, "data": "30/09/2008", "nova": false}, {"operadora": "TIM", "tecnologia": "4G", "municipio": "Rondon do Pará", "lat": -4.78131, "lon": -48.07131, "data": "10/05/2023", "nova": false}, {"operadora": "TIM", "tecnologia": "2G", "municipio": "Rondon do Pará", "lat": -4.78131, "lon": -48.07131, "data": "10/05/2023", "nova": false}, {"operadora": "TIM", "tecnologia": "3G", "municipio": "Rondon do Pará", "lat": -4.78131, "lon": -48.07131, "data": "10/05/2023", "nova": false}, {"operadora": "Vivo", "tecnologia": "2G", "municipio": "Rondon do Pará", "lat": -4.77889, "lon": -48.07417, "data": "12/07/2021", "nova": false}, {"operadora": "Vivo", "tecnologia": "3G", "municipio": "Rondon do Pará", "lat": -4.77889, "lon": -48.07417, "data": "12/07/2021", "nova": false}, {"operadora": "Vivo", "tecnologia": "4G", "municipio": "Rondon do Pará", "lat": -4.77889, "lon": -48.07417, "data": "12/07/2021", "nova": false}, {"operadora": "Vivo", "tecnologia": "5G", "municipio": "Rondon do Pará", "lat": -4.77889, "lon": -48.07417, "data": "12/07/2021", "nova": false}, {"operadora": "Vivo", "tecnologia": "4G", "municipio": "Rondon do Pará", "lat": -4.77872, "lon": -48.08975, "data": "13/12/2020", "nova": false}, {"operadora": "Claro", "tecnologia": "4G", "municipio": "Rondon do Pará", "lat": -4.77352, "lon": -48.06478, "data": "25/09/2025", "nova": true}, {"operadora": "Vivo", "tecnologia": "3G", "municipio": "Rondon do Pará", "lat": -4.77333, "lon": -48.06472, "data": "09/06/2021", "nova": false}, {"operadora": "Vivo", "tecnologia": "4G", "municipio": "Rondon do Pará", "lat": -4.77333, "lon": -48.06472, "data": "09/06/2021", "nova": false}, {"operadora": "Vivo", "tecnologia": "5G", "municipio": "Rondon do Pará", "lat": -4.77333, "lon": -48.06472, "data": "09/06/2021", "nova": false}, {"operadora": "Vivo", "tecnologia": "3G", "municipio": "Dom Eliseu", "lat": -4.439444, "lon": -47.53565, "data": "04/08/2010", "nova": false}, {"operadora": "Vivo", "tecnologia": "2G", "municipio": "Dom Eliseu", "lat": -4.439444, "lon": -47.53565, "data": "04/08/2010", "nova": false}, {"operadora": "Vivo", "tecnologia": "4G", "municipio": "Dom Eliseu", "lat": -4.439444, "lon": -47.53565, "data": "04/08/2010", "nova": false}, {"operadora": "Claro", "tecnologia": "2G", "municipio": "Rondon do Pará", "lat": -4.39577, "lon": -48.2134, "data": "04/08/2025", "nova": true}, {"operadora": "Claro", "tecnologia": "4G", "municipio": "Rondon do Pará", "lat": -4.39577, "lon": -48.2134, "data": "04/08/2025", "nova": true}, {"operadora": "Claro", "tecnologia": "3G", "municipio": "Dom Eliseu", "lat": -4.31081, "lon": -47.54828, "data": "30/10/2017", "nova": false}, {"operadora": "Claro", "tecnologia": "4G", "municipio": "Dom Eliseu", "lat": -4.31081, "lon": -47.54828, "data": "30/10/2017", "nova": false}, {"operadora": "Vivo", "tecnologia": "3G", "municipio": "Dom Eliseu", "lat": -4.30917, "lon": -47.55306, "data": "11/08/2021", "nova": false}, {"operadora": "Vivo", "tecnologia": "4G", "municipio": "Dom Eliseu", "lat": -4.30917, "lon": -47.55306, "data": "11/08/2021", "nova": false}, {"operadora": "TIM", "tecnologia": "4G", "municipio": "Dom Eliseu", "lat": -4.295603, "lon": -47.557522, "data": "20/02/2004", "nova": false}, {"operadora": "TIM", "tecnologia": "2G", "municipio": "Dom Eliseu", "lat": -4.295603, "lon": -47.557522, "data": "20/02/2004", "nova": false}, {"operadora": "TIM", "tecnologia": "3G", "municipio": "Dom Eliseu", "lat": -4.295603, "lon": -47.557522, "data": "20/02/2004", "nova": false}, {"operadora": "Vivo", "tecnologia": "4G", "municipio": "Dom Eliseu", "lat": -4.29554, "lon": -47.55745, "data": "13/12/2020", "nova": false}, {"operadora": "Vivo", "tecnologia": "3G", "municipio": "Dom Eliseu", "lat": -4.29554, "lon": -47.55745, "data": "13/12/2020", "nova": false}, {"operadora": "TIM", "tecnologia": "4G", "municipio": "Dom Eliseu", "lat": -4.287222, "lon": -47.555278, "data": "05/11/2010", "nova": false}, {"operadora": "TIM", "tecnologia": "2G", "municipio": "Dom Eliseu", "lat": -4.287222, "lon": -47.555278, "data": "05/11/2010", "nova": false}, {"operadora": "TIM", "tecnologia": "3G", "municipio": "Dom Eliseu", "lat": -4.287222, "lon": -47.555278, "data": "05/11/2010", "nova": false}, {"operadora": "TIM", "tecnologia": "5G", "municipio": "Dom Eliseu", "lat": -4.287222, "lon": -47.555278, "data": "05/11/2010", "nova": false}, {"operadora": "Claro", "tecnologia": "3G", "municipio": "Dom Eliseu", "lat": -4.28719, "lon": -47.55494, "data": "30/09/2008", "nova": false}, {"operadora": "Claro", "tecnologia": "4G", "municipio": "Dom Eliseu", "lat": -4.28719, "lon": -47.55494, "data": "30/09/2008", "nova": false}, {"operadora": "Claro", "tecnologia": "2G", "municipio": "Dom Eliseu", "lat": -4.28719, "lon": -47.55494, "data": "30/09/2008", "nova": false}, {"operadora": "Vivo", "tecnologia": "3G", "municipio": "Dom Eliseu", "lat": -4.27444, "lon": -47.55861, "data": "04/11/2002", "nova": false}, {"operadora": "Vivo", "tecnologia": "2G", "municipio": "Dom Eliseu", "lat": -4.27444, "lon": -47.55861, "data": "04/11/2002", "nova": false}, {"operadora": "Vivo", "tecnologia": "4G", "municipio": "Dom Eliseu", "lat": -4.27444, "lon": -47.55861, "data": "04/11/2002", "nova": false}, {"operadora": "TIM", "tecnologia": "4G", "municipio": "Dom Eliseu", "lat": -4.119789, "lon": -47.546189, "data": "29/03/2021", "nova": false}, {"operadora": "TIM", "tecnologia": "4G", "municipio": "Ulianópolis", "lat": -3.9679, "lon": -47.541161, "data": "07/02/2022", "nova": false}, {"operadora": "Claro", "tecnologia": "2G", "municipio": "Dom Eliseu", "lat": -3.95372, "lon": -48.02751, "data": "04/08/2025", "nova": true}, {"operadora": "Claro", "tecnologia": "4G", "municipio": "Dom Eliseu", "lat": -3.95372, "lon": -48.02751, "data": "04/08/2025", "nova": true}, {"operadora": "TIM", "tecnologia": "4G", "municipio": "Ulianópolis", "lat": -3.786775, "lon": -47.7416, "data": "14/10/2022", "nova": false}, {"operadora": "TIM", "tecnologia": "4G", "municipio": "Ulianópolis", "lat": -3.747417, "lon": -47.497028, "data": "28/07/2004", "nova": false}, {"operadora": "TIM", "tecnologia": "2G", "municipio": "Ulianópolis", "lat": -3.747417, "lon": -47.497028, "data": "28/07/2004", "nova": false}, {"operadora": "TIM", "tecnologia": "5G", "municipio": "Ulianópolis", "lat": -3.747417, "lon": -47.497028, "data": "28/07/2004", "nova": false}, {"operadora": "Vivo", "tecnologia": "2G", "municipio": "Ulianópolis", "lat": -3.74722, "lon": -47.49694, "data": "20/07/2005", "nova": false}, {"operadora": "Vivo", "tecnologia": "4G", "municipio": "Ulianópolis", "lat": -3.74722, "lon": -47.49694, "data": "20/07/2005", "nova": false}, {"operadora": "Claro", "tecnologia": "3G", "municipio": "Ulianópolis", "lat": -3.74722, "lon": -47.4969, "data": "05/11/2008", "nova": false}, {"operadora": "Claro", "tecnologia": "2G", "municipio": "Ulianópolis", "lat": -3.74722, "lon": -47.4969, "data": "05/11/2008", "nova": false}, {"operadora": "Claro", "tecnologia": "4G", "municipio": "Ulianópolis", "lat": -3.74722, "lon": -47.4969, "data": "05/11/2008", "nova": false}, {"operadora": "TIM", "tecnologia": "4G", "municipio": "Paragominas", "lat": -3.712056, "lon": -47.951667, "data": "14/10/2022", "nova": false}, {"operadora": "TIM", "tecnologia": "4G", "municipio": "Ulianópolis", "lat": -3.707889, "lon": -47.730056, "data": "14/10/2022", "nova": false}, {"operadora": "TIM", "tecnologia": "4G", "municipio": "Ulianópolis", "lat": -3.70425, "lon": -47.850733, "data": "14/10/2022", "nova": false}, {"operadora": "TIM", "tecnologia": "4G", "municipio": "Ulianópolis", "lat": -3.703, "lon": -47.563894, "data": "14/10/2022", "nova": false}, {"operadora": "Claro", "tecnologia": "3G", "municipio": "Paragominas", "lat": -3.32119, "lon": -47.46087, "data": "09/10/2023", "nova": false}, {"operadora": "Claro", "tecnologia": "4G", "municipio": "Paragominas", "lat": -3.32119, "lon": -47.46087, "data": "09/10/2023", "nova": false}, {"operadora": "MINERACAO PARAGOMINAS S.A.", "tecnologia": "4G", "municipio": "Paragominas", "lat": -3.246987, "lon": -47.737269, "data": "21/01/2025", "nova": false}, {"operadora": "Claro", "tecnologia": "2G", "municipio": "Paragominas", "lat": -3.24683, "lon": -47.73744, "data": "25/10/2022", "nova": false}, {"operadora": "Claro", "tecnologia": "4G", "municipio": "Paragominas", "lat": -3.24683, "lon": -47.73744, "data": "25/10/2022", "nova": false}, {"operadora": "Vivo", "tecnologia": "3G", "municipio": "Paragominas", "lat": -3.24667, "lon": -47.73722, "data": "31/01/2011", "nova": false}, {"operadora": "Vivo", "tecnologia": "2G", "municipio": "Paragominas", "lat": -3.24667, "lon": -47.73722, "data": "31/01/2011", "nova": false}, {"operadora": "Vivo", "tecnologia": "4G", "municipio": "Paragominas", "lat": -3.24667, "lon": -47.73722, "data": "31/01/2011", "nova": false}, {"operadora": "Vivo", "tecnologia": "4G", "municipio": "Paragominas", "lat": -3.194, "lon": -47.710269, "data": "19/12/2024", "nova": false}, {"operadora": "Vivo", "tecnologia": "4G", "municipio": "Paragominas", "lat": -3.09241, "lon": -47.66999, "data": "19/12/2024", "nova": false}, {"operadora": "Claro", "tecnologia": "4G", "municipio": "Paragominas", "lat": -3.05874, "lon": -47.41141, "data": "09/10/2023", "nova": false}, {"operadora": "Claro", "tecnologia": "2G", "municipio": "Paragominas", "lat": -3.05874, "lon": -47.41141, "data": "09/10/2023", "nova": false}, {"operadora": "Vivo", "tecnologia": "4G", "municipio": "Paragominas", "lat": -3.030111, "lon": -47.613119, "data": "19/12/2024", "nova": false}, {"operadora": "TIM", "tecnologia": "4G", "municipio": "Paragominas", "lat": -3.02849, "lon": -47.46332, "data": "23/05/2022", "nova": false}, {"operadora": "TIM", "tecnologia": "4G", "municipio": "Paragominas", "lat": -3.015306, "lon": -47.353611, "data": "05/11/2010", "nova": false}, {"operadora": "TIM", "tecnologia": "3G", "municipio": "Paragominas", "lat": -3.015306, "lon": -47.353611, "data": "05/11/2010", "nova": false}, {"operadora": "TIM", "tecnologia": "2G", "municipio": "Paragominas", "lat": -3.015306, "lon": -47.353611, "data": "05/11/2010", "nova": false}, {"operadora": "TIM", "tecnologia": "5G", "municipio": "Paragominas", "lat": -3.015306, "lon": -47.353611, "data": "05/11/2010", "nova": false}, {"operadora": "Vivo", "tecnologia": "3G", "municipio": "Paragominas", "lat": -3.01528, "lon": -47.35361, "data": "02/08/2017", "nova": false}, {"operadora": "Vivo", "tecnologia": "4G", "municipio": "Paragominas", "lat": -3.01528, "lon": -47.35361, "data": "02/08/2017", "nova": false}, {"operadora": "Vivo", "tecnologia": "5G", "municipio": "Paragominas", "lat": -3.01528, "lon": -47.35361, "data": "02/08/2017", "nova": false}, {"operadora": "Claro", "tecnologia": "2G", "municipio": "Paragominas", "lat": -3.01352, "lon": -47.35612, "data": "04/11/2022", "nova": false}, {"operadora": "Claro", "tecnologia": "4G", "municipio": "Paragominas", "lat": -3.01352, "lon": -47.35612, "data": "04/11/2022", "nova": false}, {"operadora": "Claro", "tecnologia": "5G", "municipio": "Paragominas", "lat": -3.01352, "lon": -47.35612, "data": "04/11/2022", "nova": false}, {"operadora": "Claro", "tecnologia": "3G", "municipio": "Paragominas", "lat": -3.01352, "lon": -47.35612, "data": "04/11/2022", "nova": false}, {"operadora": "Vivo", "tecnologia": "4G", "municipio": "Paragominas", "lat": -3.01075, "lon": -47.359769, "data": "08/01/2024", "nova": false}, {"operadora": "Vivo", "tecnologia": "5G", "municipio": "Paragominas", "lat": -3.01075, "lon": -47.359769, "data": "08/01/2024", "nova": false}, {"operadora": "Vivo", "tecnologia": "3G", "municipio": "Paragominas", "lat": -3.00889, "lon": -47.3475, "data": "14/06/2021", "nova": false}, {"operadora": "Vivo", "tecnologia": "4G", "municipio": "Paragominas", "lat": -3.00889, "lon": -47.3475, "data": "14/06/2021", "nova": false}, {"operadora": "Vivo", "tecnologia": "5G", "municipio": "Paragominas", "lat": -3.00889, "lon": -47.3475, "data": "14/06/2021", "nova": false}, {"operadora": "TIM", "tecnologia": "4G", "municipio": "Paragominas", "lat": -3.004278, "lon": -47.352583, "data": "08/04/2013", "nova": false}, {"operadora": "TIM", "tecnologia": "2G", "municipio": "Paragominas", "lat": -3.004278, "lon": -47.352583, "data": "08/04/2013", "nova": false}, {"operadora": "TIM", "tecnologia": "5G", "municipio": "Paragominas", "lat": -3.004278, "lon": -47.352583, "data": "08/04/2013", "nova": false}, {"operadora": "Vivo", "tecnologia": "3G", "municipio": "Paragominas", "lat": -3.00111, "lon": -47.45583, "data": "25/04/2014", "nova": false}, {"operadora": "Vivo", "tecnologia": "4G", "municipio": "Paragominas", "lat": -3.00111, "lon": -47.45583, "data": "25/04/2014", "nova": false}, {"operadora": "Vivo", "tecnologia": "5G", "municipio": "Paragominas", "lat": -3.00111, "lon": -47.45583, "data": "25/04/2014", "nova": false}, {"operadora": "Vivo", "tecnologia": "3G", "municipio": "Paragominas", "lat": -3.000875, "lon": -47.358294, "data": "15/10/2013", "nova": false}, {"operadora": "Vivo", "tecnologia": "4G", "municipio": "Paragominas", "lat": -3.000875, "lon": -47.358294, "data": "15/10/2013", "nova": false}, {"operadora": "Vivo", "tecnologia": "5G", "municipio": "Paragominas", "lat": -3.000875, "lon": -47.358294, "data": "15/10/2013", "nova": false}, {"operadora": "Claro", "tecnologia": "3G", "municipio": "Paragominas", "lat": -3.00086, "lon": -47.35831, "data": "05/11/2008", "nova": false}, {"operadora": "Claro", "tecnologia": "2G", "municipio": "Paragominas", "lat": -3.00086, "lon": -47.35831, "data": "05/11/2008", "nova": false}, {"operadora": "Claro", "tecnologia": "4G", "municipio": "Paragominas", "lat": -3.00086, "lon": -47.35831, "data": "05/11/2008", "nova": false}, {"operadora": "Claro", "tecnologia": "5G", "municipio": "Paragominas", "lat": -3.00086, "lon": -47.35831, "data": "05/11/2008", "nova": false}, {"operadora": "Vivo", "tecnologia": "4G", "municipio": "Paragominas", "lat": -2.9999, "lon": -47.34872, "data": "11/06/2024", "nova": false}, {"operadora": "Vivo", "tecnologia": "5G", "municipio": "Paragominas", "lat": -2.9999, "lon": -47.34872, "data": "11/06/2024", "nova": false}, {"operadora": "Vivo", "tecnologia": "4G", "municipio": "Paragominas", "lat": -2.999897, "lon": -47.348719, "data": "10/06/2024", "nova": false}, {"operadora": "Vivo", "tecnologia": "5G", "municipio": "Paragominas", "lat": -2.999897, "lon": -47.348719, "data": "10/06/2024", "nova": false}, {"operadora": "TIM", "tecnologia": "4G", "municipio": "Paragominas", "lat": -2.998667, "lon": -47.354972, "data": "29/01/2019", "nova": false}, {"operadora": "TIM", "tecnologia": "2G", "municipio": "Paragominas", "lat": -2.998667, "lon": -47.354972, "data": "29/01/2019", "nova": false}, {"operadora": "TIM", "tecnologia": "3G", "municipio": "Paragominas", "lat": -2.998667, "lon": -47.354972, "data": "29/01/2019", "nova": false}, {"operadora": "TIM", "tecnologia": "5G", "municipio": "Paragominas", "lat": -2.998667, "lon": -47.354972, "data": "29/01/2019", "nova": false}, {"operadora": "Claro", "tecnologia": "4G", "municipio": "Paragominas", "lat": -2.99694, "lon": -47.35667, "data": "25/10/2022", "nova": false}, {"operadora": "Claro", "tecnologia": "3G", "municipio": "Paragominas", "lat": -2.99694, "lon": -47.35667, "data": "25/10/2022", "nova": false}, {"operadora": "Claro", "tecnologia": "2G", "municipio": "Paragominas", "lat": -2.99694, "lon": -47.35667, "data": "25/10/2022", "nova": false}, {"operadora": "Claro", "tecnologia": "5G", "municipio": "Paragominas", "lat": -2.99694, "lon": -47.35667, "data": "25/10/2022", "nova": false}, {"operadora": "Vivo", "tecnologia": "3G", "municipio": "Paragominas", "lat": -2.99386, "lon": -47.34258, "data": "14/12/2020", "nova": false}, {"operadora": "Vivo", "tecnologia": "4G", "municipio": "Paragominas", "lat": -2.99386, "lon": -47.34258, "data": "30/09/2008", "nova": false}, {"operadora": "Vivo", "tecnologia": "5G", "municipio": "Paragominas", "lat": -2.99386, "lon": -47.34258, "data": "14/12/2020", "nova": false}, {"operadora": "Claro", "tecnologia": "4G", "municipio": "Paragominas", "lat": -2.99386, "lon": -47.34258, "data": "30/12/2025", "nova": true}, {"operadora": "Claro", "tecnologia": "5G", "municipio": "Paragominas", "lat": -2.99386, "lon": -47.34258, "data": "30/12/2025", "nova": true}, {"operadora": "Claro", "tecnologia": "3G", "municipio": "Paragominas", "lat": -2.99166, "lon": -47.37615, "data": "25/10/2022", "nova": false}, {"operadora": "Claro", "tecnologia": "4G", "municipio": "Paragominas", "lat": -2.99166, "lon": -47.37615, "data": "25/10/2022", "nova": false}, {"operadora": "Claro", "tecnologia": "2G", "municipio": "Paragominas", "lat": -2.99166, "lon": -47.37615, "data": "25/10/2022", "nova": false}, {"operadora": "Claro", "tecnologia": "5G", "municipio": "Paragominas", "lat": -2.99166, "lon": -47.37615, "data": "25/10/2022", "nova": false}, {"operadora": "TIM", "tecnologia": "4G", "municipio": "Paragominas", "lat": -2.99161, "lon": -47.37611, "data": "27/12/2007", "nova": false}, {"operadora": "TIM", "tecnologia": "2G", "municipio": "Paragominas", "lat": -2.99161, "lon": -47.37611, "data": "27/12/2007", "nova": false}, {"operadora": "TIM", "tecnologia": "3G", "municipio": "Paragominas", "lat": -2.99161, "lon": -47.37611, "data": "27/12/2007", "nova": false}, {"operadora": "Vivo", "tecnologia": "3G", "municipio": "Paragominas", "lat": -2.99111, "lon": -47.37055, "data": "09/06/2021", "nova": false}, {"operadora": "Vivo", "tecnologia": "2G", "municipio": "Paragominas", "lat": -2.99111, "lon": -47.37055, "data": "09/06/2021", "nova": false}, {"operadora": "Vivo", "tecnologia": "4G", "municipio": "Paragominas", "lat": -2.99111, "lon": -47.37055, "data": "09/06/2021", "nova": false}, {"operadora": "Vivo", "tecnologia": "5G", "municipio": "Paragominas", "lat": -2.99111, "lon": -47.37055, "data": "09/06/2021", "nova": false}, {"operadora": "Vivo", "tecnologia": "4G", "municipio": "Paragominas", "lat": -2.98927, "lon": -47.35972, "data": "20/09/2021", "nova": false}, {"operadora": "Vivo", "tecnologia": "5G", "municipio": "Paragominas", "lat": -2.98927, "lon": -47.35972, "data": "20/09/2021", "nova": false}, {"operadora": "TIM", "tecnologia": "4G", "municipio": "Paragominas", "lat": -2.984861, "lon": -47.451889, "data": "17/12/2002", "nova": false}, {"operadora": "TIM", "tecnologia": "2G", "municipio": "Paragominas", "lat": -2.984861, "lon": -47.451889, "data": "17/12/2002", "nova": false}, {"operadora": "TIM", "tecnologia": "3G", "municipio": "Paragominas", "lat": -2.984861, "lon": -47.451889, "data": "17/12/2002", "nova": false}, {"operadora": "Vivo", "tecnologia": "4G", "municipio": "Paragominas", "lat": -2.984739, "lon": -47.452439, "data": "26/08/2014", "nova": false}, {"operadora": "Vivo", "tecnologia": "3G", "municipio": "Paragominas", "lat": -2.984739, "lon": -47.452439, "data": "26/08/2014", "nova": false}, {"operadora": "Vivo", "tecnologia": "5G", "municipio": "Paragominas", "lat": -2.984739, "lon": -47.452439, "data": "26/08/2014", "nova": false}, {"operadora": "Claro", "tecnologia": "2G", "municipio": "Paragominas", "lat": -2.98472, "lon": -47.45167, "data": "29/07/2008", "nova": false}, {"operadora": "Claro", "tecnologia": "3G", "municipio": "Paragominas", "lat": -2.98472, "lon": -47.45167, "data": "29/07/2008", "nova": false}, {"operadora": "Claro", "tecnologia": "4G", "municipio": "Paragominas", "lat": -2.98472, "lon": -47.45167, "data": "29/07/2008", "nova": false}, {"operadora": "TIM", "tecnologia": "4G", "municipio": "Paragominas", "lat": -2.984139, "lon": -47.350417, "data": "29/03/2011", "nova": false}, {"operadora": "TIM", "tecnologia": "2G", "municipio": "Paragominas", "lat": -2.984139, "lon": -47.350417, "data": "29/03/2011", "nova": false}, {"operadora": "TIM", "tecnologia": "3G", "municipio": "Paragominas", "lat": -2.984139, "lon": -47.350417, "data": "29/03/2011", "nova": false}, {"operadora": "TIM", "tecnologia": "5G", "municipio": "Paragominas", "lat": -2.984139, "lon": -47.350417, "data": "29/03/2011", "nova": false}, {"operadora": "Vivo", "tecnologia": "3G", "municipio": "Paragominas", "lat": -2.98389, "lon": -47.35028, "data": "26/08/2014", "nova": false}, {"operadora": "Vivo", "tecnologia": "4G", "municipio": "Paragominas", "lat": -2.98389, "lon": -47.35028, "data": "26/08/2014", "nova": false}, {"operadora": "Vivo", "tecnologia": "5G", "municipio": "Paragominas", "lat": -2.98389, "lon": -47.35028, "data": "26/08/2014", "nova": false}, {"operadora": "Claro", "tecnologia": "2G", "municipio": "Paragominas", "lat": -2.98199, "lon": -47.34853, "data": "13/11/2009", "nova": false}, {"operadora": "Claro", "tecnologia": "4G", "municipio": "Paragominas", "lat": -2.98199, "lon": -47.34853, "data": "13/11/2009", "nova": false}, {"operadora": "Claro", "tecnologia": "3G", "municipio": "Paragominas", "lat": -2.98199, "lon": -47.34853, "data": "13/11/2009", "nova": false}, {"operadora": "Claro", "tecnologia": "5G", "municipio": "Paragominas", "lat": -2.98199, "lon": -47.34853, "data": "13/11/2009", "nova": false}, {"operadora": "Claro", "tecnologia": "4G", "municipio": "Paragominas", "lat": -2.98132, "lon": -47.33914, "data": "24/02/2026", "nova": true}, {"operadora": "Claro", "tecnologia": "5G", "municipio": "Paragominas", "lat": -2.98132, "lon": -47.33914, "data": "24/02/2026", "nova": true}, {"operadora": "Vivo", "tecnologia": "4G", "municipio": "Paragominas", "lat": -2.98027, "lon": -47.37913, "data": "10/11/2022", "nova": false}, {"operadora": "Vivo", "tecnologia": "5G", "municipio": "Paragominas", "lat": -2.98027, "lon": -47.37913, "data": "10/11/2022", "nova": false}, {"operadora": "Vivo", "tecnologia": "4G", "municipio": "Paragominas", "lat": -2.97833, "lon": -47.36389, "data": "16/12/2020", "nova": false}, {"operadora": "Vivo", "tecnologia": "3G", "municipio": "Paragominas", "lat": -2.97833, "lon": -47.34311, "data": "14/12/2020", "nova": false}, {"operadora": "Vivo", "tecnologia": "4G", "municipio": "Paragominas", "lat": -2.97833, "lon": -47.34311, "data": "14/12/2020", "nova": false}, {"operadora": "Vivo", "tecnologia": "5G", "municipio": "Paragominas", "lat": -2.97833, "lon": -47.34311, "data": "14/12/2020", "nova": false}, {"operadora": "Vivo", "tecnologia": "4G", "municipio": "Paragominas", "lat": -2.97806, "lon": -47.36361, "data": "27/04/2020", "nova": false}, {"operadora": "Claro", "tecnologia": "2G", "municipio": "Paragominas", "lat": -2.97806, "lon": -47.36361, "data": "04/11/2022", "nova": false}, {"operadora": "Claro", "tecnologia": "4G", "municipio": "Paragominas", "lat": -2.97806, "lon": -47.36361, "data": "04/11/2022", "nova": false}, {"operadora": "Claro", "tecnologia": "3G", "municipio": "Paragominas", "lat": -2.97806, "lon": -47.36361, "data": "04/11/2022", "nova": false}, {"operadora": "Claro", "tecnologia": "5G", "municipio": "Paragominas", "lat": -2.97806, "lon": -47.36361, "data": "04/11/2022", "nova": false}, {"operadora": "Vivo", "tecnologia": "4G", "municipio": "Paragominas", "lat": -2.976147, "lon": -47.559958, "data": "19/12/2024", "nova": false}, {"operadora": "Inovar Telecom Provedor de Internet Ltda", "tecnologia": "4G", "municipio": "Ipixuna do Pará", "lat": -2.9475083333333, "lon": -47.821372222222, "data": "27/08/2025", "nova": true}, {"operadora": "Claro", "tecnologia": "3G", "municipio": "Paragominas", "lat": -2.94694, "lon": -47.4442, "data": "08/07/2008", "nova": false}, {"operadora": "Claro", "tecnologia": "2G", "municipio": "Paragominas", "lat": -2.94694, "lon": -47.4442, "data": "08/07/2008", "nova": false}, {"operadora": "Claro", "tecnologia": "4G", "municipio": "Paragominas", "lat": -2.94694, "lon": -47.4442, "data": "08/07/2008", "nova": false}, {"operadora": "Vivo", "tecnologia": "2G", "municipio": "Paragominas", "lat": -2.94694, "lon": -47.44417, "data": "21/12/2001", "nova": false}, {"operadora": "Vivo", "tecnologia": "3G", "municipio": "Paragominas", "lat": -2.94694, "lon": -47.44417, "data": "21/12/2001", "nova": false}, {"operadora": "Vivo", "tecnologia": "4G", "municipio": "Paragominas", "lat": -2.94694, "lon": -47.44417, "data": "21/12/2001", "nova": false}, {"operadora": "TIM", "tecnologia": "4G", "municipio": "Paragominas", "lat": -2.945722, "lon": -46.744861, "data": "29/03/2021", "nova": false}, {"operadora": "TIM", "tecnologia": "4G", "municipio": "Tomé-Açu", "lat": -2.9339222, "lon": -48.3586472, "data": "14/11/2025", "nova": true}, {"operadora": "TIM", "tecnologia": "4G", "municipio": "Tomé-Açu", "lat": -2.8688889, "lon": -48.1585278, "data": "14/11/2025", "nova": true}, {"operadora": "Claro", "tecnologia": "2G", "municipio": "Tomé-Açu", "lat": -2.85022, "lon": -48.23158, "data": "09/10/2023", "nova": false}, {"operadora": "Claro", "tecnologia": "4G", "municipio": "Tomé-Açu", "lat": -2.85022, "lon": -48.23158, "data": "09/10/2023", "nova": false}, {"operadora": "Vivo", "tecnologia": "2G", "municipio": "Ipixuna do Pará", "lat": -2.83056, "lon": -47.91667, "data": "16/01/2007", "nova": false}, {"operadora": "Vivo", "tecnologia": "3G", "municipio": "Ipixuna do Pará", "lat": -2.83056, "lon": -47.91667, "data": "16/01/2007", "nova": false}, {"operadora": "Vivo", "tecnologia": "4G", "municipio": "Ipixuna do Pará", "lat": -2.83056, "lon": -47.91667, "data": "16/01/2007", "nova": false}, {"operadora": "TIM", "tecnologia": "4G", "municipio": "Tomé-Açu", "lat": -2.8281667, "lon": -48.2816111, "data": "14/11/2025", "nova": true}, {"operadora": "TIM", "tecnologia": "4G", "municipio": "Tomé-Açu", "lat": -2.7945139, "lon": -48.4711, "data": "14/11/2025", "nova": true}, {"operadora": "TIM", "tecnologia": "4G", "municipio": "Tomé-Açu", "lat": -2.7356944, "lon": -48.3506111, "data": "14/11/2025", "nova": true}, {"operadora": "Vivo", "tecnologia": "4G", "municipio": "Ipixuna do Pará", "lat": -2.724417, "lon": -47.463306, "data": "16/06/2025", "nova": true}, {"operadora": "Vivo", "tecnologia": "2G", "municipio": "Ipixuna do Pará", "lat": -2.72417, "lon": -47.46306, "data": "19/07/2012", "nova": false}, {"operadora": "Vivo", "tecnologia": "4G", "municipio": "Ipixuna do Pará", "lat": -2.72417, "lon": -47.46306, "data": "19/07/2012", "nova": false}, {"operadora": "TIM", "tecnologia": "4G", "municipio": "Ipixuna do Pará", "lat": -2.6680806, "lon": -47.9918111, "data": "14/11/2025", "nova": true}, {"operadora": "Vivo", "tecnologia": "4G", "municipio": "Ipixuna do Pará", "lat": -2.593619, "lon": -47.579281, "data": "23/07/2025", "nova": true}, {"operadora": "Vivo", "tecnologia": "3G", "municipio": "Ipixuna do Pará", "lat": -2.57333, "lon": -47.49667, "data": "29/12/2010", "nova": false}, {"operadora": "Vivo", "tecnologia": "2G", "municipio": "Ipixuna do Pará", "lat": -2.57333, "lon": -47.49667, "data": "29/12/2010", "nova": false}, {"operadora": "Vivo", "tecnologia": "4G", "municipio": "Ipixuna do Pará", "lat": -2.57333, "lon": -47.49667, "data": "29/12/2010", "nova": false}, {"operadora": "Claro", "tecnologia": "3G", "municipio": "Ipixuna do Pará", "lat": -2.56177, "lon": -47.49844, "data": "17/02/2012", "nova": false}, {"operadora": "Claro", "tecnologia": "2G", "municipio": "Ipixuna do Pará", "lat": -2.56177, "lon": -47.49844, "data": "17/02/2012", "nova": false}, {"operadora": "Claro", "tecnologia": "4G", "municipio": "Ipixuna do Pará", "lat": -2.56177, "lon": -47.49844, "data": "17/02/2012", "nova": false}, {"operadora": "Claro", "tecnologia": "5G", "municipio": "Ipixuna do Pará", "lat": -2.56177, "lon": -47.49844, "data": "17/02/2012", "nova": false}, {"operadora": "Claro", "tecnologia": "2G", "municipio": "Ipixuna do Pará", "lat": -2.561767, "lon": -47.498444, "data": "24/10/2022", "nova": false}, {"operadora": "TIM", "tecnologia": "4G", "municipio": "Ipixuna do Pará", "lat": -2.55639, "lon": -47.49694, "data": "29/03/2011", "nova": false}, {"operadora": "TIM", "tecnologia": "2G", "municipio": "Ipixuna do Pará", "lat": -2.55639, "lon": -47.49694, "data": "29/03/2011", "nova": false}, {"operadora": "Vivo", "tecnologia": "4G", "municipio": "Ipixuna do Pará", "lat": -2.51379, "lon": -47.60295, "data": "27/01/2026", "nova": true}, {"operadora": "TIM", "tecnologia": "4G", "municipio": "Aurora do Pará", "lat": -2.4884167, "lon": -47.9498889, "data": "14/11/2025", "nova": true}, {"operadora": "Claro", "tecnologia": "2G", "municipio": "Capitão Poço", "lat": -2.48367, "lon": -47.18367, "data": "12/08/2024", "nova": false}, {"operadora": "Claro", "tecnologia": "4G", "municipio": "Capitão Poço", "lat": -2.48367, "lon": -47.18367, "data": "12/08/2024", "nova": false}, {"operadora": "Vivo", "tecnologia": "3G", "municipio": "Tomé-Açu", "lat": -2.48222, "lon": -48.33167, "data": "25/07/2008", "nova": false}, {"operadora": "Vivo", "tecnologia": "2G", "municipio": "Tomé-Açu", "lat": -2.48222, "lon": -48.33167, "data": "25/07/2008", "nova": false}, {"operadora": "Vivo", "tecnologia": "4G", "municipio": "Tomé-Açu", "lat": -2.48222, "lon": -48.33167, "data": "25/07/2008", "nova": false}, {"operadora": "TIM", "tecnologia": "4G", "municipio": "Garrafão do Norte", "lat": -2.44, "lon": -47.14473, "data": "16/07/2021", "nova": false}, {"operadora": "Vivo", "tecnologia": "4G", "municipio": "Tomé-Açu", "lat": -2.42061, "lon": -48.25308, "data": "13/12/2020", "nova": false}, {"operadora": "Vivo", "tecnologia": "5G", "municipio": "Tomé-Açu", "lat": -2.42061, "lon": -48.25308, "data": "13/12/2020", "nova": false}, {"operadora": "TIM", "tecnologia": "2G", "municipio": "Tomé-Açu", "lat": -2.419389, "lon": -48.242722, "data": "29/11/2024", "nova": false}, {"operadora": "TIM", "tecnologia": "3G", "municipio": "Tomé-Açu", "lat": -2.419389, "lon": -48.242722, "data": "29/11/2024", "nova": false}, {"operadora": "TIM", "tecnologia": "3G", "municipio": "Tomé-Açu", "lat": -2.41917, "lon": -48.2425, "data": "20/11/2007", "nova": false}, {"operadora": "TIM", "tecnologia": "2G", "municipio": "Tomé-Açu", "lat": -2.41917, "lon": -48.2425, "data": "20/11/2007", "nova": false}, {"operadora": "Claro", "tecnologia": "2G", "municipio": "Tomé-Açu", "lat": -2.41875, "lon": -48.24193, "data": "29/11/2022", "nova": false}, {"operadora": "Claro", "tecnologia": "4G", "municipio": "Tomé-Açu", "lat": -2.41875, "lon": -48.24193, "data": "29/11/2022", "nova": false}, {"operadora": "Vivo", "tecnologia": "2G", "municipio": "Tomé-Açu", "lat": -2.41874, "lon": -48.24196, "data": "13/12/2020", "nova": false}, {"operadora": "Vivo", "tecnologia": "4G", "municipio": "Tomé-Açu", "lat": -2.41874, "lon": -48.24196, "data": "13/12/2020", "nova": false}, {"operadora": "Vivo", "tecnologia": "5G", "municipio": "Tomé-Açu", "lat": -2.41874, "lon": -48.24196, "data": "13/12/2020", "nova": false}, {"operadora": "Claro", "tecnologia": "2G", "municipio": "Tomé-Açu", "lat": -2.41781, "lon": -48.1525, "data": "29/07/2008", "nova": false}, {"operadora": "Claro", "tecnologia": "3G", "municipio": "Tomé-Açu", "lat": -2.41781, "lon": -48.1525, "data": "29/07/2008", "nova": false}, {"operadora": "Claro", "tecnologia": "4G", "municipio": "Tomé-Açu", "lat": -2.41781, "lon": -48.1525, "data": "29/07/2008", "nova": false}, {"operadora": "TIM", "tecnologia": "4G", "municipio": "Tomé-Açu", "lat": -2.417806, "lon": -48.152472, "data": "22/03/2006", "nova": false}, {"operadora": "TIM", "tecnologia": "2G", "municipio": "Tomé-Açu", "lat": -2.417806, "lon": -48.152472, "data": "22/03/2006", "nova": false}, {"operadora": "TIM", "tecnologia": "3G", "municipio": "Tomé-Açu", "lat": -2.417806, "lon": -48.152472, "data": "22/03/2006", "nova": false}, {"operadora": "Vivo", "tecnologia": "3G", "municipio": "Tomé-Açu", "lat": -2.41778, "lon": -48.1525, "data": "09/06/2021", "nova": false}, {"operadora": "Vivo", "tecnologia": "2G", "municipio": "Tomé-Açu", "lat": -2.41778, "lon": -48.1525, "data": "09/06/2021", "nova": false}, {"operadora": "Vivo", "tecnologia": "4G", "municipio": "Tomé-Açu", "lat": -2.41778, "lon": -48.1525, "data": "09/06/2021", "nova": false}, {"operadora": "Vivo", "tecnologia": "5G", "municipio": "Tomé-Açu", "lat": -2.41778, "lon": -48.1525, "data": "09/06/2021", "nova": false}, {"operadora": "Claro", "tecnologia": "3G", "municipio": "Tomé-Açu", "lat": -2.41346, "lon": -48.15397, "data": "27/03/2015", "nova": false}, {"operadora": "Claro", "tecnologia": "4G", "municipio": "Tomé-Açu", "lat": -2.41346, "lon": -48.15397, "data": "27/03/2015", "nova": false}, {"operadora": "Claro", "tecnologia": "2G", "municipio": "Tomé-Açu", "lat": -2.41346, "lon": -48.15397, "data": "27/03/2015", "nova": false}, {"operadora": "Vivo", "tecnologia": "4G", "municipio": "Tomé-Açu", "lat": -2.4128, "lon": -48.13908, "data": "17/05/2023", "nova": false}, {"operadora": "Claro", "tecnologia": "2G", "municipio": "Tomé-Açu", "lat": -2.41027, "lon": -48.25717, "data": "08/07/2008", "nova": false}, {"operadora": "Claro", "tecnologia": "3G", "municipio": "Tomé-Açu", "lat": -2.41027, "lon": -48.25717, "data": "08/07/2008", "nova": false}, {"operadora": "Claro", "tecnologia": "4G", "municipio": "Tomé-Açu", "lat": -2.41027, "lon": -48.25717, "data": "08/07/2008", "nova": false}, {"operadora": "Vivo", "tecnologia": "3G", "municipio": "Tomé-Açu", "lat": -2.41, "lon": -48.25694, "data": "13/09/2021", "nova": false}, {"operadora": "Vivo", "tecnologia": "2G", "municipio": "Tomé-Açu", "lat": -2.41, "lon": -48.25694, "data": "13/09/2021", "nova": false}, {"operadora": "Vivo", "tecnologia": "4G", "municipio": "Tomé-Açu", "lat": -2.41, "lon": -48.25694, "data": "13/09/2021", "nova": false}, {"operadora": "Vivo", "tecnologia": "5G", "municipio": "Tomé-Açu", "lat": -2.41, "lon": -48.25694, "data": "13/09/2021", "nova": false}, {"operadora": "Vivo", "tecnologia": "4G", "municipio": "Tomé-Açu", "lat": -2.39958, "lon": -48.22836, "data": "09/06/2021", "nova": false}, {"operadora": "Vivo", "tecnologia": "3G", "municipio": "Tomé-Açu", "lat": -2.39958, "lon": -48.22836, "data": "09/06/2021", "nova": false}, {"operadora": "Vivo", "tecnologia": "5G", "municipio": "Tomé-Açu", "lat": -2.39958, "lon": -48.22836, "data": "09/06/2021", "nova": false}, {"operadora": "TIM", "tecnologia": "4G", "municipio": "Ipixuna do Pará", "lat": -2.39043, "lon": -47.54498, "data": "11/08/2021", "nova": false}, {"operadora": "Claro", "tecnologia": "3G", "municipio": "Ipixuna do Pará", "lat": -2.3895, "lon": -47.54191, "data": "03/03/2015", "nova": false}, {"operadora": "Claro", "tecnologia": "2G", "municipio": "Ipixuna do Pará", "lat": -2.3895, "lon": -47.54191, "data": "03/03/2015", "nova": false}, {"operadora": "Claro", "tecnologia": "4G", "municipio": "Ipixuna do Pará", "lat": -2.3895, "lon": -47.54191, "data": "03/03/2015", "nova": false}, {"operadora": "Vivo", "tecnologia": "4G", "municipio": "Tomé-Açu", "lat": -2.36515, "lon": -48.126739, "data": "12/06/2024", "nova": false}, {"operadora": "TIM", "tecnologia": "4G", "municipio": "Nova Esperança do Piriá", "lat": -2.36, "lon": -47.068083, "data": "29/03/2021", "nova": false}, {"operadora": "Vivo", "tecnologia": "2G", "municipio": "Aurora do Pará", "lat": -2.32361, "lon": -47.56472, "data": "24/12/2013", "nova": false}, {"operadora": "Vivo", "tecnologia": "3G", "municipio": "Aurora do Pará", "lat": -2.32361, "lon": -47.56472, "data": "24/12/2013", "nova": false}, {"operadora": "Vivo", "tecnologia": "4G", "municipio": "Aurora do Pará", "lat": -2.32361, "lon": -47.56472, "data": "24/12/2013", "nova": false}, {"operadora": "Vivo", "tecnologia": "4G", "municipio": "Aurora do Pará", "lat": -2.28985, "lon": -47.565019, "data": "22/12/2023", "nova": false}, {"operadora": "TIM", "tecnologia": "4G", "municipio": "Nova Esperança do Piriá", "lat": -2.286994, "lon": -46.970664, "data": "09/05/2022", "nova": false}, {"operadora": "Claro", "tecnologia": "2G", "municipio": "Nova Esperança do Piriá", "lat": -2.27222, "lon": -46.971, "data": "16/03/2009", "nova": false}, {"operadora": "Claro", "tecnologia": "3G", "municipio": "Nova Esperança do Piriá", "lat": -2.27222, "lon": -46.971, "data": "16/03/2009", "nova": false}, {"operadora": "Claro", "tecnologia": "4G", "municipio": "Nova Esperança do Piriá", "lat": -2.27222, "lon": -46.971, "data": "16/03/2009", "nova": false}, {"operadora": "TIM", "tecnologia": "4G", "municipio": "Nova Esperança do Piriá", "lat": -2.269416, "lon": -46.969694, "data": "03/05/2022", "nova": false}, {"operadora": "Claro", "tecnologia": "2G", "municipio": "Nova Esperança do Piriá", "lat": -2.26722, "lon": -46.97306, "data": "29/10/2010", "nova": false}, {"operadora": "Claro", "tecnologia": "3G", "municipio": "Nova Esperança do Piriá", "lat": -2.26722, "lon": -46.97306, "data": "29/10/2010", "nova": false}, {"operadora": "Claro", "tecnologia": "4G", "municipio": "Nova Esperança do Piriá", "lat": -2.26722, "lon": -46.97306, "data": "29/10/2010", "nova": false}, {"operadora": "Vivo", "tecnologia": "4G", "municipio": "Nova Esperança do Piriá", "lat": -2.26722, "lon": -46.97306, "data": "13/12/2020", "nova": false}, {"operadora": "Claro", "tecnologia": "5G", "municipio": "Nova Esperança do Piriá", "lat": -2.26722, "lon": -46.97306, "data": "29/10/2010", "nova": false}, {"operadora": "Vivo", "tecnologia": "4G", "municipio": "Tomé-Açu", "lat": -2.24154, "lon": -48.16069, "data": "20/09/2021", "nova": false}, {"operadora": "Vivo", "tecnologia": "5G", "municipio": "Tomé-Açu", "lat": -2.24154, "lon": -48.16069, "data": "20/09/2021", "nova": false}, {"operadora": "TIM", "tecnologia": "4G", "municipio": "Capitão Poço", "lat": -2.203944, "lon": -47.226306, "data": "29/03/2021", "nova": false}, {"operadora": "Claro", "tecnologia": "2G", "municipio": "Capitão Poço", "lat": -2.20367, "lon": -47.22699, "data": "30/08/2023", "nova": false}, {"operadora": "Claro", "tecnologia": "4G", "municipio": "Capitão Poço", "lat": -2.20367, "lon": -47.22699, "data": "30/08/2023", "nova": false}, {"operadora": "Vivo", "tecnologia": "4G", "municipio": "Acará", "lat": -2.15662, "lon": -48.40387, "data": "16/12/2024", "nova": false}, {"operadora": "Vivo", "tecnologia": "3G", "municipio": "Aurora do Pará", "lat": -2.13586, "lon": -47.55686, "data": "29/12/2010", "nova": false}, {"operadora": "Vivo", "tecnologia": "2G", "municipio": "Aurora do Pará", "lat": -2.13586, "lon": -47.55686, "data": "29/12/2010", "nova": false}, {"operadora": "Claro", "tecnologia": "3G", "municipio": "Aurora do Pará", "lat": -2.13586, "lon": -47.55686, "data": "02/11/2017", "nova": false}, {"operadora": "Vivo", "tecnologia": "4G", "municipio": "Aurora do Pará", "lat": -2.13586, "lon": -47.55686, "data": "29/12/2010", "nova": false}, {"operadora": "Claro", "tecnologia": "3G", "municipio": "Aurora do Pará", "lat": -2.13468, "lon": -47.55692, "data": "29/05/2023", "nova": false}, {"operadora": "Claro", "tecnologia": "2G", "municipio": "Aurora do Pará", "lat": -2.13468, "lon": -47.55692, "data": "29/05/2023", "nova": false}, {"operadora": "Claro", "tecnologia": "4G", "municipio": "Aurora do Pará", "lat": -2.13468, "lon": -47.55692, "data": "29/05/2023", "nova": false}, {"operadora": "TIM", "tecnologia": "2G", "municipio": "Aurora do Pará", "lat": -2.133161, "lon": -47.558428, "data": "30/12/2008", "nova": false}, {"operadora": "TIM", "tecnologia": "3G", "municipio": "Aurora do Pará", "lat": -2.133161, "lon": -47.558428, "data": "30/12/2008", "nova": false}, {"operadora": "TIM", "tecnologia": "4G", "municipio": "Aurora do Pará", "lat": -2.133161, "lon": -47.558428, "data": "30/12/2008", "nova": false}, {"operadora": "TIM", "tecnologia": "4G", "municipio": "Viseu", "lat": -2.061556, "lon": -46.677639, "data": "29/03/2021", "nova": false}, {"operadora": "TIM", "tecnologia": "4G", "municipio": "Mãe do Rio", "lat": -2.05731, "lon": -47.53914, "data": "13/12/2018", "nova": false}, {"operadora": "TIM", "tecnologia": "2G", "municipio": "Mãe do Rio", "lat": -2.05731, "lon": -47.53914, "data": "13/12/2018", "nova": false}, {"operadora": "TIM", "tecnologia": "3G", "municipio": "Mãe do Rio", "lat": -2.05731, "lon": -47.53914, "data": "13/12/2018", "nova": false}, {"operadora": "TIM", "tecnologia": "4G", "municipio": "Mãe do Rio", "lat": -2.057306, "lon": -47.539139, "data": "25/10/2024", "nova": false}, {"operadora": "TIM", "tecnologia": "3G", "municipio": "Mãe do Rio", "lat": -2.057306, "lon": -47.539139, "data": "25/10/2024", "nova": false}, {"operadora": "Vivo", "tecnologia": "3G", "municipio": "Mãe do Rio", "lat": -2.05417, "lon": -47.54444, "data": "20/07/2005", "nova": false}, {"operadora": "Vivo", "tecnologia": "2G", "municipio": "Mãe do Rio", "lat": -2.05417, "lon": -47.54444, "data": "20/07/2005", "nova": false}, {"operadora": "Vivo", "tecnologia": "4G", "municipio": "Mãe do Rio", "lat": -2.05417, "lon": -47.54444, "data": "20/07/2005", "nova": false}, {"operadora": "TIM", "tecnologia": "4G", "municipio": "Mãe do Rio", "lat": -2.05, "lon": -47.55361, "data": "01/12/2004", "nova": false}, {"operadora": "TIM", "tecnologia": "2G", "municipio": "Mãe do Rio", "lat": -2.05, "lon": -47.55361, "data": "01/12/2004", "nova": false}, {"operadora": "TIM", "tecnologia": "3G", "municipio": "Mãe do Rio", "lat": -2.05, "lon": -47.55361, "data": "01/12/2004", "nova": false}, {"operadora": "Vivo", "tecnologia": "4G", "municipio": "Acará", "lat": -2.0485, "lon": -48.2815, "data": "13/06/2025", "nova": true}, {"operadora": "Claro", "tecnologia": "2G", "municipio": "Mãe do Rio", "lat": -2.04713, "lon": -47.55323, "data": "30/09/2008", "nova": false}, {"operadora": "Claro", "tecnologia": "3G", "municipio": "Mãe do Rio", "lat": -2.04713, "lon": -47.55323, "data": "30/09/2008", "nova": false}, {"operadora": "Claro", "tecnologia": "4G", "municipio": "Mãe do Rio", "lat": -2.04713, "lon": -47.55323, "data": "30/09/2008", "nova": false}, {"operadora": "Claro", "tecnologia": "2G", "municipio": "Mãe do Rio", "lat": -2.046944, "lon": -47.553056, "data": "24/10/2022", "nova": false}, {"operadora": "Vivo", "tecnologia": "3G", "municipio": "Mãe do Rio", "lat": -2.04147, "lon": -47.56019, "data": "14/12/2020", "nova": false}, {"operadora": "Claro", "tecnologia": "4G", "municipio": "Mãe do Rio", "lat": -2.04147, "lon": -47.56019, "data": "28/08/2025", "nova": true}, {"operadora": "Claro", "tecnologia": "4G", "municipio": "Aurora do Pará", "lat": -2.03722, "lon": -47.75111, "data": "23/11/2022", "nova": false}, {"operadora": "Claro", "tecnologia": "2G", "municipio": "Aurora do Pará", "lat": -2.03722, "lon": -47.75111, "data": "23/11/2022", "nova": false}, {"operadora": "TIM", "tecnologia": "4G", "municipio": "Aurora do Pará", "lat": -2.032066667, "lon": -47.749846, "data": "28/05/2021", "nova": false}, {"operadora": "TIM", "tecnologia": "4G", "municipio": "Garrafão do Norte", "lat": -2.027830556, "lon": -46.91866944, "data": "13/07/2021", "nova": false}, {"operadora": "Vivo", "tecnologia": "4G", "municipio": "Garrafão do Norte", "lat": -2.01171, "lon": -47.02037, "data": "05/02/2025", "nova": false}, {"operadora": "TIM", "tecnologia": "4G", "municipio": "Cachoeira do Piriá", "lat": -2.010417, "lon": -46.462472, "data": "29/03/2021", "nova": false}, {"operadora": "Claro", "tecnologia": "3G", "municipio": "Concórdia do Pará", "lat": -2.00092, "lon": -47.94533, "data": "24/06/2024", "nova": false}, {"operadora": "Vivo", "tecnologia": "3G", "municipio": "Concórdia do Pará", "lat": -2.00083, "lon": -47.94528, "data": "05/12/2017", "nova": false}, {"operadora": "Vivo", "tecnologia": "4G", "municipio": "Concórdia do Pará", "lat": -2.00083, "lon": -47.94528, "data": "05/12/2017", "nova": false}, {"operadora": "Vivo", "tecnologia": "4G", "municipio": "São Domingos do Capim", "lat": -1.997531, "lon": -47.896411, "data": "16/12/2024", "nova": false}, {"operadora": "TIM", "tecnologia": "4G", "municipio": "Concórdia do Pará", "lat": -1.994722, "lon": -47.942306, "data": "28/03/2022", "nova": false}, {"operadora": "TIM", "tecnologia": "5G", "municipio": "Concórdia do Pará", "lat": -1.994722, "lon": -47.942306, "data": "28/03/2022", "nova": false}, {"operadora": "TIM", "tecnologia": "4G", "municipio": "Garrafão do Norte", "lat": -1.992372222, "lon": -46.95083333, "data": "13/07/2021", "nova": false}, {"operadora": "Claro", "tecnologia": "2G", "municipio": "Concórdia do Pará", "lat": -1.9911, "lon": -47.94742, "data": "25/10/2022", "nova": false}, {"operadora": "Claro", "tecnologia": "4G", "municipio": "Concórdia do Pará", "lat": -1.9911, "lon": -47.94742, "data": "25/10/2022", "nova": false}, {"operadora": "Vivo", "tecnologia": "4G", "municipio": "Concórdia do Pará", "lat": -1.988978, "lon": -48.042344, "data": "13/06/2025", "nova": true}, {"operadora": "Vivo", "tecnologia": "3G", "municipio": "Concórdia do Pará", "lat": -1.98528, "lon": -47.94111, "data": "06/05/2003", "nova": false}, {"operadora": "Vivo", "tecnologia": "2G", "municipio": "Concórdia do Pará", "lat": -1.98528, "lon": -47.94111, "data": "06/05/2003", "nova": false}, {"operadora": "Vivo", "tecnologia": "4G", "municipio": "Concórdia do Pará", "lat": -1.98528, "lon": -47.94111, "data": "06/05/2003", "nova": false}, {"operadora": "Vivo", "tecnologia": "5G", "municipio": "Concórdia do Pará", "lat": -1.98528, "lon": -47.94111, "data": "06/05/2003", "nova": false}, {"operadora": "Claro", "tecnologia": "3G", "municipio": "Concórdia do Pará", "lat": -1.98527, "lon": -47.94111, "data": "26/10/2017", "nova": false}, {"operadora": "TIM", "tecnologia": "4G", "municipio": "Mãe do Rio", "lat": -1.98125, "lon": -47.4365, "data": "29/03/2021", "nova": false}, {"operadora": "Claro", "tecnologia": "4G", "municipio": "Mãe do Rio", "lat": -1.98047, "lon": -47.52292, "data": "30/08/2023", "nova": false}, {"operadora": "Claro", "tecnologia": "2G", "municipio": "Mãe do Rio", "lat": -1.98047, "lon": -47.52292, "data": "30/08/2023", "nova": false}, {"operadora": "Claro", "tecnologia": "3G", "municipio": "Acará", "lat": -1.96286, "lon": -48.3507, "data": "25/10/2022", "nova": false}, {"operadora": "Claro", "tecnologia": "2G", "municipio": "Acará", "lat": -1.96286, "lon": -48.3507, "data": "25/10/2022", "nova": false}, {"operadora": "Claro", "tecnologia": "4G", "municipio": "Acará", "lat": -1.96286, "lon": -48.3507, "data": "25/10/2022", "nova": false}, {"operadora": "TIM", "tecnologia": "4G", "municipio": "Irituia", "lat": -1.961417, "lon": -47.303222, "data": "29/03/2021", "nova": false}, {"operadora": "Vivo", "tecnologia": "3G", "municipio": "Acará", "lat": -1.96111, "lon": -48.1975, "data": "14/03/2018", "nova": false}, {"operadora": "Vivo", "tecnologia": "4G", "municipio": "Acará", "lat": -1.96111, "lon": -48.1975, "data": "14/03/2018", "nova": false}, {"operadora": "TIM", "tecnologia": "4G", "municipio": "Acará", "lat": -1.961, "lon": -48.198306, "data": "03/09/2018", "nova": false}, {"operadora": "TIM", "tecnologia": "3G", "municipio": "Acará", "lat": -1.961, "lon": -48.198306, "data": "03/09/2018", "nova": false}, {"operadora": "TIM", "tecnologia": "5G", "municipio": "Acará", "lat": -1.961, "lon": -48.198306, "data": "03/09/2018", "nova": false}, {"operadora": "Claro", "tecnologia": "2G", "municipio": "Acará", "lat": -1.95971, "lon": -48.19738, "data": "06/02/2013", "nova": false}, {"operadora": "Claro", "tecnologia": "4G", "municipio": "Acará", "lat": -1.95971, "lon": -48.19738, "data": "06/02/2013", "nova": false}, {"operadora": "Claro", "tecnologia": "3G", "municipio": "Acará", "lat": -1.95971, "lon": -48.19738, "data": "06/02/2013", "nova": false}, {"operadora": "TIM", "tecnologia": "4G", "municipio": "Acará", "lat": -1.95616666, "lon": -48.350888, "data": "09/07/2021", "nova": false}, {"operadora": "Claro", "tecnologia": "2G", "municipio": "Garrafão do Norte", "lat": -1.93723, "lon": -47.04569, "data": "21/10/2010", "nova": false}, {"operadora": "Claro", "tecnologia": "3G", "municipio": "Garrafão do Norte", "lat": -1.93723, "lon": -47.04569, "data": "21/10/2010", "nova": false}, {"operadora": "Claro", "tecnologia": "4G", "municipio": "Garrafão do Norte", "lat": -1.93723, "lon": -47.04569, "data": "21/10/2010", "nova": false}, {"operadora": "Vivo", "tecnologia": "4G", "municipio": "Garrafão do Norte", "lat": -1.93556, "lon": -47.04944, "data": "16/03/2020", "nova": false}, {"operadora": "Vivo", "tecnologia": "3G", "municipio": "Garrafão do Norte", "lat": -1.93556, "lon": -47.04944, "data": "16/03/2020", "nova": false}, {"operadora": "TIM", "tecnologia": "4G", "municipio": "Garrafão do Norte", "lat": -1.930365, "lon": -47.044188, "data": "02/07/2021", "nova": false}, {"operadora": "Claro", "tecnologia": "3G", "municipio": "Garrafão do Norte", "lat": -1.93013, "lon": -47.0506, "data": "20/05/2009", "nova": false}, {"operadora": "Claro", "tecnologia": "2G", "municipio": "Garrafão do Norte", "lat": -1.93013, "lon": -47.0506, "data": "20/05/2009", "nova": false}, {"operadora": "Claro", "tecnologia": "4G", "municipio": "Garrafão do Norte", "lat": -1.93013, "lon": -47.0506, "data": "20/05/2009", "nova": false}, {"operadora": "TIM", "tecnologia": "4G", "municipio": "Capitão Poço", "lat": -1.9144222, "lon": -47.162686, "data": "29/03/2021", "nova": false}, {"operadora": "Vivo", "tecnologia": "4G", "municipio": "Capitão Poço", "lat": -1.907139, "lon": -47.156417, "data": "05/02/2025", "nova": false}, {"operadora": "Vivo", "tecnologia": "4G", "municipio": "Concórdia do Pará", "lat": -1.902561, "lon": -48.02485, "data": "08/03/2024", "nova": false}, {"operadora": "TIM", "tecnologia": "4G", "municipio": "Irituia", "lat": -1.870028, "lon": -47.391806, "data": "29/03/2021", "nova": false}, {"operadora": "Vivo", "tecnologia": "4G", "municipio": "Capitão Poço", "lat": -1.857, "lon": -47.055081, "data": "05/05/2025", "nova": true}, {"operadora": "TIM", "tecnologia": "4G", "municipio": "São Domingos do Capim", "lat": -1.844792, "lon": -47.639236, "data": "29/03/2021", "nova": false}, {"operadora": "Vivo", "tecnologia": "4G", "municipio": "Acará", "lat": -1.8385, "lon": -48.08241, "data": "16/12/2024", "nova": false}, {"operadora": "Claro", "tecnologia": "2G", "municipio": "Cachoeira do Piriá", "lat": -1.83626, "lon": -46.52388, "data": "20/08/2024", "nova": false}, {"operadora": "Claro", "tecnologia": "4G", "municipio": "Cachoeira do Piriá", "lat": -1.83626, "lon": -46.52388, "data": "20/08/2024", "nova": false}, {"operadora": "Claro", "tecnologia": "3G", "municipio": "Acará", "lat": -1.82454, "lon": -48.20322, "data": "26/02/2015", "nova": false}, {"operadora": "Claro", "tecnologia": "2G", "municipio": "Acará", "lat": -1.82454, "lon": -48.20322, "data": "26/02/2015", "nova": false}, {"operadora": "Claro", "tecnologia": "4G", "municipio": "Acará", "lat": -1.82454, "lon": -48.20322, "data": "26/02/2015", "nova": false}, {"operadora": "Claro", "tecnologia": "2G", "municipio": "Irituia", "lat": -1.80225, "lon": -47.33032, "data": "28/11/2022", "nova": false}, {"operadora": "Claro", "tecnologia": "4G", "municipio": "Irituia", "lat": -1.80225, "lon": -47.33032, "data": "28/11/2022", "nova": false}, {"operadora": "Vivo", "tecnologia": "4G", "municipio": "Capitão Poço", "lat": -1.777534, "lon": -47.238317, "data": "16/12/2024", "nova": false}, {"operadora": "TIM", "tecnologia": "4G", "municipio": "Irituia", "lat": -1.772028, "lon": -47.44038, "data": "01/10/2008", "nova": false}, {"operadora": "TIM", "tecnologia": "3G", "municipio": "Irituia", "lat": -1.772028, "lon": -47.44038, "data": "01/10/2008", "nova": false}, {"operadora": "TIM", "tecnologia": "2G", "municipio": "Irituia", "lat": -1.772028, "lon": -47.44038, "data": "01/10/2008", "nova": false}, {"operadora": "TIM", "tecnologia": "4G", "municipio": "Irituia", "lat": -1.77197, "lon": -47.44036, "data": "05/03/2015", "nova": false}, {"operadora": "TIM", "tecnologia": "3G", "municipio": "Irituia", "lat": -1.77197, "lon": -47.44036, "data": "05/03/2015", "nova": false}, {"operadora": "Vivo", "tecnologia": "2G", "municipio": "Irituia", "lat": -1.77194, "lon": -47.44028, "data": "25/07/2008", "nova": false}, {"operadora": "Vivo", "tecnologia": "3G", "municipio": "Irituia", "lat": -1.77194, "lon": -47.44028, "data": "25/07/2008", "nova": false}, {"operadora": "Vivo", "tecnologia": "4G", "municipio": "Irituia", "lat": -1.77194, "lon": -47.44028, "data": "25/07/2008", "nova": false}, {"operadora": "Claro", "tecnologia": "2G", "municipio": "Irituia", "lat": -1.7717, "lon": -47.44012, "data": "06/02/2013", "nova": false}, {"operadora": "Claro", "tecnologia": "4G", "municipio": "Irituia", "lat": -1.7717, "lon": -47.44012, "data": "06/02/2013", "nova": false}, {"operadora": "Claro", "tecnologia": "3G", "municipio": "Irituia", "lat": -1.7717, "lon": -47.44012, "data": "06/02/2013", "nova": false}, {"operadora": "TIM", "tecnologia": "4G", "municipio": "Capitão Poço", "lat": -1.76875, "lon": -47.168528, "data": "06/10/2021", "nova": false}, {"operadora": "TIM", "tecnologia": "4G", "municipio": "Cachoeira do Piriá", "lat": -1.767043, "lon": -46.543229, "data": "03/05/2022", "nova": false}, {"operadora": "TIM", "tecnologia": "4G", "municipio": "Acará", "lat": -1.759333, "lon": -48.407972, "data": "03/05/2022", "nova": false}, {"operadora": "TIM", "tecnologia": "4G", "municipio": "Cachoeira do Piriá", "lat": -1.757734, "lon": -46.54308, "data": "14/02/2022", "nova": false}, {"operadora": "Claro", "tecnologia": "2G", "municipio": "Cachoeira do Piriá", "lat": -1.75611, "lon": -46.54361, "data": "16/03/2009", "nova": false}, {"operadora": "Claro", "tecnologia": "3G", "municipio": "Cachoeira do Piriá", "lat": -1.75611, "lon": -46.54361, "data": "16/03/2009", "nova": false}, {"operadora": "Claro", "tecnologia": "4G", "municipio": "Cachoeira do Piriá", "lat": -1.75611, "lon": -46.54361, "data": "16/03/2009", "nova": false}, {"operadora": "Claro", "tecnologia": "5G", "municipio": "Cachoeira do Piriá", "lat": -1.75611, "lon": -46.54361, "data": "16/03/2009", "nova": false}, {"operadora": "TIM", "tecnologia": "2G", "municipio": "Capitão Poço", "lat": -1.754178, "lon": -47.068892, "data": "05/11/2010", "nova": false}, {"operadora": "TIM", "tecnologia": "4G", "municipio": "Capitão Poço", "lat": -1.754178, "lon": -47.068892, "data": "05/11/2010", "nova": false}, {"operadora": "TIM", "tecnologia": "3G", "municipio": "Capitão Poço", "lat": -1.754178, "lon": -47.068892, "data": "05/11/2010", "nova": false}, {"operadora": "Vivo", "tecnologia": "3G", "municipio": "Capitão Poço", "lat": -1.75417, "lon": -47.06889, "data": "12/12/2017", "nova": false}, {"operadora": "Vivo", "tecnologia": "4G", "municipio": "Capitão Poço", "lat": -1.75417, "lon": -47.06889, "data": "12/12/2017", "nova": false}, {"operadora": "TIM", "tecnologia": "4G", "municipio": "Cachoeira do Piriá", "lat": -1.751055, "lon": -46.399305, "data": "06/05/2021", "nova": false}, {"operadora": "Vivo", "tecnologia": "4G", "municipio": "Capitão Poço", "lat": -1.75056, "lon": -47.05672, "data": "13/12/2020", "nova": false}, {"operadora": "Claro", "tecnologia": "3G", "municipio": "Capitão Poço", "lat": -1.74966, "lon": -47.07005, "data": "25/02/2015", "nova": false}, {"operadora": "Claro", "tecnologia": "4G", "municipio": "Capitão Poço", "lat": -1.74966, "lon": -47.07005, "data": "25/02/2015", "nova": false}, {"operadora": "TIM", "tecnologia": "3G", "municipio": "Capitão Poço", "lat": -1.748611, "lon": -47.060278, "data": "30/12/2004", "nova": false}, {"operadora": "TIM", "tecnologia": "2G", "municipio": "Capitão Poço", "lat": -1.748611, "lon": -47.060278, "data": "30/12/2004", "nova": false}, {"operadora": "TIM", "tecnologia": "4G", "municipio": "Capitão Poço", "lat": -1.748611, "lon": -47.060278, "data": "30/12/2004", "nova": false}, {"operadora": "TIM", "tecnologia": "5G", "municipio": "Capitão Poço", "lat": -1.748611, "lon": -47.060278, "data": "30/12/2004", "nova": false}, {"operadora": "Claro", "tecnologia": "3G", "municipio": "Capitão Poço", "lat": -1.7486, "lon": -47.06069, "data": "30/09/2008", "nova": false}, {"operadora": "Claro", "tecnologia": "4G", "municipio": "Capitão Poço", "lat": -1.7486, "lon": -47.06069, "data": "30/09/2008", "nova": false}, {"operadora": "Claro", "tecnologia": "2G", "municipio": "Capitão Poço", "lat": -1.7486, "lon": -47.06069, "data": "30/09/2008", "nova": false}, {"operadora": "Claro", "tecnologia": "2G", "municipio": "Capitão Poço", "lat": -1.748056, "lon": -47.06, "data": "24/10/2022", "nova": false}, {"operadora": "Claro", "tecnologia": "2G", "municipio": "Irituia", "lat": -1.74232, "lon": -47.49906, "data": "25/10/2022", "nova": false}, {"operadora": "Claro", "tecnologia": "4G", "municipio": "Irituia", "lat": -1.74232, "lon": -47.49906, "data": "25/10/2022", "nova": false}, {"operadora": "Vivo", "tecnologia": "4G", "municipio": "Capitão Poço", "lat": -1.74142, "lon": -47.07581, "data": "13/12/2020", "nova": false}, {"operadora": "Vivo", "tecnologia": "3G", "municipio": "Capitão Poço", "lat": -1.74083, "lon": -47.05917, "data": "20/07/2005", "nova": false}, {"operadora": "Vivo", "tecnologia": "2G", "municipio": "Capitão Poço", "lat": -1.74083, "lon": -47.05917, "data": "20/07/2005", "nova": false}, {"operadora": "Vivo", "tecnologia": "4G", "municipio": "Capitão Poço", "lat": -1.74083, "lon": -47.05917, "data": "20/07/2005", "nova": false}, {"operadora": "Vivo", "tecnologia": "4G", "municipio": "Capitão Poço", "lat": -1.735823, "lon": -47.17269, "data": "23/07/2025", "nova": true}, {"operadora": "TIM", "tecnologia": "4G", "municipio": "Capitão Poço", "lat": -1.7355555, "lon": -47.1741111, "data": "11/11/2021", "nova": false}, {"operadora": "TIM", "tecnologia": "4G", "municipio": "São Domingos do Capim", "lat": -1.689822, "lon": -47.766844, "data": "03/05/2022", "nova": false}, {"operadora": "Claro", "tecnologia": "3G", "municipio": "São Domingos do Capim", "lat": -1.68725, "lon": -47.76521, "data": "05/01/2015", "nova": false}, {"operadora": "Vivo", "tecnologia": "3G", "municipio": "São Domingos do Capim", "lat": -1.68694, "lon": -47.765, "data": "15/07/2005", "nova": false}, {"operadora": "Vivo", "tecnologia": "2G", "municipio": "São Domingos do Capim", "lat": -1.68694, "lon": -47.765, "data": "15/07/2005", "nova": false}, {"operadora": "Vivo", "tecnologia": "4G", "municipio": "São Domingos do Capim", "lat": -1.68694, "lon": -47.765, "data": "15/07/2005", "nova": false}, {"operadora": "Claro", "tecnologia": "3G", "municipio": "São Domingos do Capim", "lat": -1.6869, "lon": -47.765, "data": "05/01/2015", "nova": false}, {"operadora": "Claro", "tecnologia": "4G", "municipio": "São Domingos do Capim", "lat": -1.6869, "lon": -47.765, "data": "05/01/2015", "nova": false}, {"operadora": "Claro", "tecnologia": "2G", "municipio": "São Domingos do Capim", "lat": -1.6869, "lon": -47.765, "data": "05/01/2015", "nova": false}, {"operadora": "TIM", "tecnologia": "4G", "municipio": "Viseu", "lat": -1.682111, "lon": -46.711806, "data": "29/03/2021", "nova": false}, {"operadora": "TIM", "tecnologia": "4G", "municipio": "São Domingos do Capim", "lat": -1.679558, "lon": -47.771983, "data": "03/05/2022", "nova": false}, {"operadora": "Vivo", "tecnologia": "4G", "municipio": "São Domingos do Capim", "lat": -1.6751, "lon": -47.77088, "data": "13/12/2020", "nova": false}, {"operadora": "Claro", "tecnologia": "3G", "municipio": "São Domingos do Capim", "lat": -1.67507, "lon": -47.77076, "data": "07/11/2022", "nova": false}, {"operadora": "Claro", "tecnologia": "2G", "municipio": "São Domingos do Capim", "lat": -1.67507, "lon": -47.77076, "data": "07/11/2022", "nova": false}, {"operadora": "Claro", "tecnologia": "4G", "municipio": "São Domingos do Capim", "lat": -1.67507, "lon": -47.77076, "data": "07/11/2022", "nova": false}, {"operadora": "Vivo", "tecnologia": "2G", "municipio": "Irituia", "lat": -1.67417, "lon": -47.49833, "data": "17/08/2021", "nova": false}, {"operadora": "Vivo", "tecnologia": "3G", "municipio": "Irituia", "lat": -1.67417, "lon": -47.49833, "data": "17/08/2021", "nova": false}, {"operadora": "Vivo", "tecnologia": "4G", "municipio": "Irituia", "lat": -1.67417, "lon": -47.49833, "data": "17/08/2021", "nova": false}, {"operadora": "Claro", "tecnologia": "4G", "municipio": "Capitão Poço", "lat": -1.65248, "lon": -47.11465, "data": "13/11/2024", "nova": false}, {"operadora": "Claro", "tecnologia": "3G", "municipio": "Capitão Poço", "lat": -1.65248, "lon": -47.11465, "data": "13/11/2024", "nova": false}, {"operadora": "Claro", "tecnologia": "2G", "municipio": "Santa Luzia do Pará", "lat": -1.6321, "lon": -46.80059, "data": "02/09/2024", "nova": false}, {"operadora": "Claro", "tecnologia": "4G", "municipio": "Santa Luzia do Pará", "lat": -1.6321, "lon": -46.80059, "data": "02/09/2024", "nova": false}, {"operadora": "TIM", "tecnologia": "4G", "municipio": "São Miguel do Guamá", "lat": -1.619722, "lon": -47.48275, "data": "20/02/2004", "nova": false}, {"operadora": "TIM", "tecnologia": "2G", "municipio": "São Miguel do Guamá", "lat": -1.619722, "lon": -47.48275, "data": "20/02/2004", "nova": false}, {"operadora": "TIM", "tecnologia": "3G", "municipio": "São Miguel do Guamá", "lat": -1.619722, "lon": -47.48275, "data": "20/02/2004", "nova": false}, {"operadora": "Vivo", "tecnologia": "4G", "municipio": "São Miguel do Guamá", "lat": -1.61972, "lon": -47.4825, "data": "22/11/2017", "nova": false}, {"operadora": "Claro", "tecnologia": "2G", "municipio": "São Miguel do Guamá", "lat": -1.618889, "lon": -47.483611, "data": "24/10/2022", "nova": false}, {"operadora": "Claro", "tecnologia": "2G", "municipio": "São Miguel do Guamá", "lat": -1.61888, "lon": -47.48361, "data": "30/09/2008", "nova": false}, {"operadora": "Claro", "tecnologia": "4G", "municipio": "São Miguel do Guamá", "lat": -1.61888, "lon": -47.48361, "data": "30/09/2008", "nova": false}, {"operadora": "Claro", "tecnologia": "3G", "municipio": "São Miguel do Guamá", "lat": -1.61888, "lon": -47.48361, "data": "30/09/2008", "nova": false}, {"operadora": "Vivo", "tecnologia": "4G", "municipio": "São Miguel do Guamá", "lat": -1.615167, "lon": -47.48075, "data": "25/07/2008", "nova": false}, {"operadora": "Vivo", "tecnologia": "3G", "municipio": "São Miguel do Guamá", "lat": -1.615167, "lon": -47.48075, "data": "25/07/2008", "nova": false}, {"operadora": "Vivo", "tecnologia": "2G", "municipio": "São Miguel do Guamá", "lat": -1.615167, "lon": -47.48075, "data": "25/07/2008", "nova": false}, {"operadora": "Vivo", "tecnologia": "3G", "municipio": "São Miguel do Guamá", "lat": -1.61336, "lon": -47.46556, "data": "14/12/2020", "nova": false}, {"operadora": "Vivo", "tecnologia": "4G", "municipio": "São Miguel do Guamá", "lat": -1.61336, "lon": -47.46556, "data": "14/12/2020", "nova": false}, {"operadora": "TIM", "tecnologia": "4G", "municipio": "São Miguel do Guamá", "lat": -1.60556, "lon": -47.48253, "data": "05/11/2010", "nova": false}, {"operadora": "TIM", "tecnologia": "2G", "municipio": "São Miguel do Guamá", "lat": -1.60556, "lon": -47.48253, "data": "05/11/2010", "nova": false}, {"operadora": "TIM", "tecnologia": "3G", "municipio": "São Miguel do Guamá", "lat": -1.60556, "lon": -47.48253, "data": "05/11/2010", "nova": false}, {"operadora": "Vivo", "tecnologia": "4G", "municipio": "São Miguel do Guamá", "lat": -1.60556, "lon": -47.4825, "data": "22/11/2017", "nova": false}, {"operadora": "TIM", "tecnologia": "2G", "municipio": "São Miguel do Guamá", "lat": -1.602378, "lon": -47.473356, "data": "17/01/2024", "nova": false}, {"operadora": "TIM", "tecnologia": "4G", "municipio": "São Miguel do Guamá", "lat": -1.602378, "lon": -47.473356, "data": "17/01/2024", "nova": false}, {"operadora": "Vivo", "tecnologia": "3G", "municipio": "São Miguel do Guamá", "lat": -1.60236, "lon": -47.47628, "data": "14/06/2021", "nova": false}, {"operadora": "Vivo", "tecnologia": "4G", "municipio": "São Miguel do Guamá", "lat": -1.60236, "lon": -47.47628, "data": "14/06/2021", "nova": false}, {"operadora": "Claro", "tecnologia": "3G", "municipio": "São Miguel do Guamá", "lat": -1.60236, "lon": -47.47627, "data": "27/05/2022", "nova": false}, {"operadora": "Claro", "tecnologia": "4G", "municipio": "São Miguel do Guamá", "lat": -1.60236, "lon": -47.47627, "data": "27/05/2022", "nova": false}, {"operadora": "Claro", "tecnologia": "2G", "municipio": "São Miguel do Guamá", "lat": -1.60236, "lon": -47.47627, "data": "27/05/2022", "nova": false}, {"operadora": "TIM", "tecnologia": "4G", "municipio": "Viseu", "lat": -1.59425, "lon": -46.1600833, "data": "11/08/2021", "nova": false}, {"operadora": "TIM", "tecnologia": "3G", "municipio": "Viseu", "lat": -1.59425, "lon": -46.1600833, "data": "11/08/2021", "nova": false}, {"operadora": "Claro", "tecnologia": "4G", "municipio": "Capitão Poço", "lat": -1.57672, "lon": -47.03311, "data": "30/08/2023", "nova": false}, {"operadora": "Claro", "tecnologia": "2G", "municipio": "Capitão Poço", "lat": -1.57672, "lon": -47.03311, "data": "30/08/2023", "nova": false}, {"operadora": "TIM", "tecnologia": "3G", "municipio": "Ourém", "lat": -1.551292, "lon": -47.116828, "data": "30/12/2004", "nova": false}, {"operadora": "TIM", "tecnologia": "2G", "municipio": "Ourém", "lat": -1.551292, "lon": -47.116828, "data": "30/12/2004", "nova": false}, {"operadora": "TIM", "tecnologia": "4G", "municipio": "Ourém", "lat": -1.551292, "lon": -47.116828, "data": "30/12/2004", "nova": false}, {"operadora": "Claro", "tecnologia": "3G", "municipio": "Ourém", "lat": -1.54512, "lon": -47.11432, "data": "12/12/2014", "nova": false}, {"operadora": "Claro", "tecnologia": "4G", "municipio": "Ourém", "lat": -1.54512, "lon": -47.11432, "data": "12/12/2014", "nova": false}, {"operadora": "Claro", "tecnologia": "5G", "municipio": "Ourém", "lat": -1.54512, "lon": -47.11432, "data": "12/12/2014", "nova": false}, {"operadora": "Vivo", "tecnologia": "3G", "municipio": "Santa Luzia do Pará", "lat": -1.531919, "lon": -46.893581, "data": "26/06/2001", "nova": false}, {"operadora": "Vivo", "tecnologia": "2G", "municipio": "Santa Luzia do Pará", "lat": -1.531919, "lon": -46.893581, "data": "26/06/2001", "nova": false}, {"operadora": "Vivo", "tecnologia": "4G", "municipio": "Santa Luzia do Pará", "lat": -1.531919, "lon": -46.893581, "data": "26/06/2001", "nova": false}, {"operadora": "Claro", "tecnologia": "3G", "municipio": "Santa Luzia do Pará", "lat": -1.53167, "lon": -46.89333, "data": "26/10/2017", "nova": false}, {"operadora": "TIM", "tecnologia": "4G", "municipio": "Santa Luzia do Pará", "lat": -1.52575, "lon": -46.904861, "data": "02/07/2021", "nova": false}, {"operadora": "Claro", "tecnologia": "3G", "municipio": "Santa Luzia do Pará", "lat": -1.52064, "lon": -46.90252, "data": "24/01/2024", "nova": false}, {"operadora": "Claro", "tecnologia": "2G", "municipio": "Bujaru", "lat": -1.51944, "lon": -48.03527, "data": "03/10/2022", "nova": false}, {"operadora": "Claro", "tecnologia": "4G", "municipio": "Bujaru", "lat": -1.51944, "lon": -48.03527, "data": "03/10/2022", "nova": false}, {"operadora": "Claro", "tecnologia": "3G", "municipio": "Bujaru", "lat": -1.51944, "lon": -48.03527, "data": "03/10/2022", "nova": false}, {"operadora": "TIM", "tecnologia": "4G", "municipio": "Bujaru", "lat": -1.51779166, "lon": -48.04123611, "data": "03/05/2022", "nova": false}, {"operadora": "Vivo", "tecnologia": "3G", "municipio": "Santa Luzia do Pará", "lat": -1.51667, "lon": -46.90417, "data": "08/07/2019", "nova": false}, {"operadora": "Vivo", "tecnologia": "4G", "municipio": "Santa Luzia do Pará", "lat": -1.51667, "lon": -46.90417, "data": "08/07/2019", "nova": false}, {"operadora": "Vivo", "tecnologia": "3G", "municipio": "Bujaru", "lat": -1.51471, "lon": -48.04416, "data": "09/06/2021", "nova": false}, {"operadora": "Vivo", "tecnologia": "4G", "municipio": "Bujaru", "lat": -1.51471, "lon": -48.04416, "data": "09/06/2021", "nova": false}, {"operadora": "Claro", "tecnologia": "2G", "municipio": "Bujaru", "lat": -1.514333, "lon": -48.042111, "data": "24/10/2022", "nova": false}, {"operadora": "Claro", "tecnologia": "4G", "municipio": "Bujaru", "lat": -1.51433, "lon": -48.04211, "data": "16/12/2014", "nova": false}, {"operadora": "Claro", "tecnologia": "2G", "municipio": "Bujaru", "lat": -1.51433, "lon": -48.04211, "data": "16/12/2014", "nova": false}, {"operadora": "Claro", "tecnologia": "3G", "municipio": "Bujaru", "lat": -1.51433, "lon": -48.04211, "data": "16/12/2014", "nova": false}, {"operadora": "TIM", "tecnologia": "4G", "municipio": "Acará", "lat": -1.513944, "lon": -48.415306, "data": "15/06/2021", "nova": false}, {"operadora": "Vivo", "tecnologia": "4G", "municipio": "Acará", "lat": -1.513539, "lon": -48.4153, "data": "05/02/2025", "nova": false}, {"operadora": "Vivo", "tecnologia": "5G", "municipio": "Acará", "lat": -1.513539, "lon": -48.4153, "data": "05/02/2025", "nova": false}, {"operadora": "Vivo", "tecnologia": "4G", "municipio": "Belém", "lat": -1.503033, "lon": -48.461814, "data": "04/08/2025", "nova": true}, {"operadora": "Vivo", "tecnologia": "5G", "municipio": "Belém", "lat": -1.503033, "lon": -48.461814, "data": "04/08/2025", "nova": true}, {"operadora": "Claro", "tecnologia": "5G", "municipio": "Belém", "lat": -1.50007, "lon": -48.46055, "data": "12/09/2025", "nova": true}, {"operadora": "Claro", "tecnologia": "3G", "municipio": "Belém", "lat": -1.50007, "lon": -48.46055, "data": "12/09/2025", "nova": true}, {"operadora": "Claro", "tecnologia": "4G", "municipio": "Belém", "lat": -1.50007, "lon": -48.46055, "data": "12/09/2025", "nova": true}, {"operadora": "TIM", "tecnologia": "4G", "municipio": "Belém", "lat": -1.500003, "lon": -48.460944, "data": "28/05/2025", "nova": true}, {"operadora": "TIM", "tecnologia": "5G", "municipio": "Belém", "lat": -1.500003, "lon": -48.460944, "data": "28/05/2025", "nova": true}, {"operadora": "TIM", "tecnologia": "4G", "municipio": "Viseu", "lat": -1.488389, "lon": -46.644556, "data": "29/03/2021", "nova": false}, {"operadora": "Claro", "tecnologia": "4G", "municipio": "Belém", "lat": -1.47683, "lon": -48.46006, "data": "18/09/2025", "nova": true}, {"operadora": "Claro", "tecnologia": "5G", "municipio": "Belém", "lat": -1.47683, "lon": -48.46006, "data": "18/09/2025", "nova": true}, {"operadora": "Vivo", "tecnologia": "4G", "municipio": "São Miguel do Guamá", "lat": -1.476806, "lon": -47.646583, "data": "05/02/2025", "nova": false}]